{
	"format_version": "1.12.0",
	"minecraft:geometry": [
		{
			"description": {
				"identifier": "geometry.unknown",
				"texture_width": 64,
				"texture_height": 64,
				"visible_bounds_width": 4,
				"visible_bounds_height": 4.5,
				"visible_bounds_offset": [0, 1.75, 0]
			},
			"bones": [
				{
					"name": "bipedHead",
					"pivot": [0, 24, 0]
				},
				{
					"name": "armorHead",
					"parent": "bipedHead",
					"pivot": [0, 24, 0]
				},
				{
					"name": "bone5",
					"parent": "armorHead",
					"pivot": [0, 0, 0],
					"cubes": [
						{
							"origin": [-3, 23.9, -4.6],
							"size": [6, 1.1, 1],
							"uv": {
								"north": {"uv": [41, 15], "uv_size": [6, 1]},
								"east": {"uv": [46, 15], "uv_size": [1, 1]},
								"south": {"uv": [41, 15], "uv_size": [6, 1]},
								"west": {"uv": [46, 15], "uv_size": [1, 1]},
								"up": {"uv": [47, 16], "uv_size": [-6, -1]},
								"down": {"uv": [47, 16], "uv_size": [-6, -1]}
							}
						},
						{
							"origin": [-1, 25, -4.6],
							"size": [2, 1, 1],
							"uv": {
								"north": {"uv": [43, 14], "uv_size": [2, 1]},
								"east": {"uv": [43, 14], "uv_size": [1, 1]},
								"south": {"uv": [43, 14], "uv_size": [2, 1]},
								"west": {"uv": [44, 14], "uv_size": [1, 1]},
								"up": {"uv": [43, 15], "uv_size": [2, -1]},
								"down": {"uv": [45, 15], "uv_size": [-2, -1]}
							}
						},
						{
							"origin": [-2, 25, -4.3],
							"size": [1, 1, 0.7],
							"uv": {
								"north": {"uv": [42, 14], "uv_size": [1, 1]},
								"east": {"uv": [43, 14], "uv_size": [1, 1]},
								"south": {"uv": [43, 14], "uv_size": [2, 1]},
								"west": {"uv": [44, 14], "uv_size": [1, 1]},
								"up": {"uv": [43, 15], "uv_size": [2, -1]},
								"down": {"uv": [45, 15], "uv_size": [-2, -1]}
							}
						},
						{
							"origin": [1, 25, -4.3],
							"size": [1, 1, 0.7],
							"uv": {
								"north": {"uv": [42, 14], "uv_size": [1, 1]},
								"east": {"uv": [43, 14], "uv_size": [1, 1]},
								"south": {"uv": [43, 14], "uv_size": [2, 1]},
								"west": {"uv": [44, 14], "uv_size": [1, 1]},
								"up": {"uv": [43, 15], "uv_size": [2, -1]},
								"down": {"uv": [45, 15], "uv_size": [-2, -1]}
							}
						},
						{
							"origin": [-3, 29, -4.6],
							"size": [6, 2, 1],
							"uv": {
								"north": {"uv": [41, 9], "uv_size": [6, 2]},
								"east": {"uv": [43, 14], "uv_size": [1, 1]},
								"south": {"uv": [43, 14], "uv_size": [2, 1]},
								"west": {"uv": [44, 14], "uv_size": [1, 1]},
								"up": {"uv": [41, 10], "uv_size": [6, -1]},
								"down": {"uv": [47, 11], "uv_size": [-6, -1]}
							}
						},
						{
							"origin": [-3, 26, -4.3],
							"size": [6, 3, 1],
							"uv": {
								"north": {"uv": [41, 11], "uv_size": [6, 3]},
								"east": {"uv": [43, 14], "uv_size": [1, 1]},
								"south": {"uv": [41, 9], "uv_size": [6, 2]},
								"west": {"uv": [44, 14], "uv_size": [1, 1]},
								"up": {"uv": [41, 10], "uv_size": [6, -1]},
								"down": {"uv": [47, 11], "uv_size": [-6, -1]}
							}
						},
						{
							"origin": [2, 25, -4.6],
							"size": [2, 1, 1],
							"uv": {
								"north": {"uv": [46, 14], "uv_size": [2, 1]},
								"east": {"uv": [43, 14], "uv_size": [1, 1]},
								"south": {"uv": [43, 14], "uv_size": [2, 1]},
								"west": {"uv": [47, 14], "uv_size": [1, 1]},
								"up": {"uv": [46, 15], "uv_size": [2, -1]},
								"down": {"uv": [45, 15], "uv_size": [-2, -1]}
							}
						},
						{
							"origin": [-4, 25, -4.6],
							"size": [2, 1, 1],
							"uv": {
								"north": {"uv": [40, 14], "uv_size": [2, 1]},
								"east": {"uv": [43, 14], "uv_size": [1, 1]},
								"south": {"uv": [43, 14], "uv_size": [2, 1]},
								"west": {"uv": [41, 14], "uv_size": [1, 1]},
								"up": {"uv": [40, 15], "uv_size": [2, -1]},
								"down": {"uv": [40, 15], "uv_size": [2, -1]}
							}
						},
						{
							"origin": [-4, 26, -4.6],
							"size": [1, 4, 1],
							"uv": {
								"north": {"uv": [40, 10], "uv_size": [1, 4]},
								"east": {"uv": [40, 10], "uv_size": [1, 4]},
								"south": {"uv": [43, 14], "uv_size": [2, 1]},
								"west": {"uv": [40, 10], "uv_size": [1, 4]},
								"up": {"uv": [40, 15], "uv_size": [2, -1]},
								"down": {"uv": [40, 15], "uv_size": [2, -1]}
							}
						},
						{
							"origin": [3, 26, -4.6],
							"size": [1, 4, 1],
							"uv": {
								"north": {"uv": [47, 10], "uv_size": [1, 4]},
								"east": {"uv": [40, 10], "uv_size": [1, 4]},
								"south": {"uv": [43, 14], "uv_size": [2, 1]},
								"west": {"uv": [40, 10], "uv_size": [1, 4]},
								"up": {"uv": [40, 15], "uv_size": [2, -1]},
								"down": {"uv": [40, 15], "uv_size": [2, -1]}
							}
						},
						{
							"origin": [-2, 31, -4.6],
							"size": [4, 1, 1],
							"uv": {
								"north": {"uv": [42, 8], "uv_size": [4, 1]},
								"east": {"uv": [42, 8], "uv_size": [4, 1]},
								"south": {"uv": [42, 8], "uv_size": [4, 1]},
								"west": {"uv": [42, 8], "uv_size": [4, 1]},
								"up": {"uv": [46, 9], "uv_size": [-4, -1]},
								"down": {"uv": [46, 9], "uv_size": [-4, -1]}
							}
						},
						{
							"origin": [-3.9, 24, -4.2],
							"size": [7.8, 8, 1],
							"uv": {
								"north": {"uv": [8, 8], "uv_size": [8, 8]},
								"east": {"uv": [42, 8], "uv_size": [4, 1]},
								"south": {"uv": [8, 8], "uv_size": [8, 8]},
								"west": {"uv": [42, 8], "uv_size": [4, 1]},
								"up": {"uv": [46, 9], "uv_size": [-4, -1]},
								"down": {"uv": [46, 9], "uv_size": [-4, -1]}
							}
						},
						{
							"origin": [-3.9, 24, 3.2],
							"size": [7.8, 8, 1],
							"uv": {
								"north": {"uv": [24, 8], "uv_size": [8, 8]},
								"east": {"uv": [42, 8], "uv_size": [4, 1]},
								"south": {"uv": [24, 8], "uv_size": [8, 8]},
								"west": {"uv": [42, 8], "uv_size": [4, 1]},
								"up": {"uv": [46, 9], "uv_size": [-4, -1]},
								"down": {"uv": [46, 9], "uv_size": [-4, -1]}
							}
						},
						{
							"origin": [-4, 25, 3.5],
							"size": [8, 5, 1],
							"uv": {
								"north": {"uv": [56, 10], "uv_size": [8, 5]},
								"east": {"uv": [63, 10], "uv_size": [1, 5]},
								"south": {"uv": [56, 10], "uv_size": [8, 5]},
								"west": {"uv": [56, 10], "uv_size": [1, 5]},
								"up": {"uv": [64, 11], "uv_size": [-8, -1]},
								"down": {"uv": [64, 15], "uv_size": [-8, -1]}
							}
						},
						{
							"origin": [-3, 30, 3.5],
							"size": [6, 1, 1],
							"uv": {
								"north": {"uv": [56, 10], "uv_size": [8, 5]},
								"east": {"uv": [57, 9], "uv_size": [1, 1]},
								"south": {"uv": [57, 9], "uv_size": [6, 1]},
								"west": {"uv": [57, 9], "uv_size": [1, 1]},
								"up": {"uv": [63, 10], "uv_size": [-6, -1]},
								"down": {"uv": [64, 15], "uv_size": [-8, -1]}
							}
						},
						{
							"origin": [-3, 23.9, 3.5],
							"size": [6, 1.1, 1],
							"uv": {
								"north": {"uv": [57, 15], "uv_size": [6, 1]},
								"east": {"uv": [57, 9], "uv_size": [1, 1]},
								"south": {"uv": [57, 15], "uv_size": [6, 1]},
								"west": {"uv": [57, 15], "uv_size": [1, 1]},
								"up": {"uv": [63, 10], "uv_size": [-6, -1]},
								"down": {"uv": [63, 16], "uv_size": [-6, -1]}
							}
						},
						{
							"origin": [-2, 31, 3.5],
							"size": [4, 1.1, 1],
							"uv": {
								"north": {"uv": [56, 10], "uv_size": [8, 5]},
								"east": {"uv": [58, 8], "uv_size": [4, 1]},
								"south": {"uv": [58, 8], "uv_size": [4, 1]},
								"west": {"uv": [58, 8], "uv_size": [4, 1]},
								"up": {"uv": [62, 9], "uv_size": [-4, -1]},
								"down": {"uv": [64, 15], "uv_size": [-8, -1]}
							}
						},
						{
							"origin": [-3.9, 32.2, -3.9],
							"size": [7.8, 7.8, 1],
							"pivot": [3.9, 32.2, -3.9],
							"rotation": [-90, 0, 0],
							"uv": {
								"north": {"uv": [8, 0], "uv_size": [8, 8]},
								"east": {"uv": [42, 8], "uv_size": [4, 1]},
								"south": {"uv": [24, 8], "uv_size": [8, 8]},
								"west": {"uv": [42, 8], "uv_size": [4, 1]},
								"up": {"uv": [46, 9], "uv_size": [-4, -1]},
								"down": {"uv": [46, 9], "uv_size": [-4, -1]}
							}
						},
						{
							"origin": [-3, 32.2, -3.4],
							"size": [6, 6, 1],
							"pivot": [3, 32.2, -3],
							"rotation": [-90, 0, 0],
							"uv": {
								"north": {"uv": [41, 1], "uv_size": [6, 6]},
								"east": {"uv": [41, 1], "uv_size": [1, 6]},
								"south": {"uv": [24, 8], "uv_size": [8, 8]},
								"west": {"uv": [41, 1], "uv_size": [1, 6]},
								"up": {"uv": [47, 2], "uv_size": [-6, -1]},
								"down": {"uv": [47, 7], "uv_size": [-6, -1]}
							}
						},
						{
							"origin": [-2, 32.2, -4.5],
							"size": [4, 1.1, 1],
							"pivot": [2, 32.2, -4.1],
							"rotation": [-90, 0, 0],
							"uv": {
								"north": {"uv": [42, 7], "uv_size": [4, 1]},
								"east": {"uv": [42, 7], "uv_size": [4, 1]},
								"south": {"uv": [42, 7], "uv_size": [4, 1]},
								"west": {"uv": [42, 7], "uv_size": [4, 1]},
								"up": {"uv": [46, 8], "uv_size": [-4, -1]},
								"down": {"uv": [46, 8], "uv_size": [-4, -1]}
							}
						},
						{
							"origin": [-2, 32.2, 2.6],
							"size": [4, 1.1, 1],
							"pivot": [2, 32.2, 3],
							"rotation": [-90, 0, 0],
							"uv": {
								"north": {"uv": [42, 7], "uv_size": [4, 1]},
								"east": {"uv": [42, 7], "uv_size": [4, 1]},
								"south": {"uv": [42, 7], "uv_size": [4, 1]},
								"west": {"uv": [42, 7], "uv_size": [4, 1]},
								"up": {"uv": [46, 8], "uv_size": [-4, -1]},
								"down": {"uv": [46, 8], "uv_size": [-4, -1]}
							}
						},
						{
							"origin": [0, 32.2, -2.4],
							"size": [3, 1.1, 1],
							"pivot": [3, 32.2, -2],
							"rotation": [-90, 90, 0],
							"uv": {
								"north": {"uv": [40, 3], "uv_size": [1, 3]},
								"east": {"uv": [40, 3], "uv_size": [1, 3]},
								"south": {"uv": [40, 3], "uv_size": [1, 3]},
								"west": {"uv": [40, 3], "uv_size": [1, 3]},
								"up": {"uv": [41, 6], "uv_size": [-1, -3]},
								"down": {"uv": [41, 6], "uv_size": [-1, -3]}
							}
						},
						{
							"origin": [-7.1, 32.2, -2.4],
							"size": [3, 1.1, 1],
							"pivot": [-4.1, 32.2, -2],
							"rotation": [-90, 90, 0],
							"uv": {
								"north": {"uv": [40, 3], "uv_size": [1, 3]},
								"east": {"uv": [40, 3], "uv_size": [1, 3]},
								"south": {"uv": [40, 3], "uv_size": [1, 3]},
								"west": {"uv": [40, 3], "uv_size": [1, 3]},
								"up": {"uv": [41, 6], "uv_size": [-1, -3]},
								"down": {"uv": [41, 6], "uv_size": [-1, -3]}
							}
						},
						{
							"origin": [-3.7, 24, 4],
							"size": [7.8, 8, 1],
							"pivot": [4.2, 24, 4],
							"rotation": [0, -90, 0],
							"uv": {
								"north": {"uv": [8, 8], "uv_size": [-8, 8]},
								"east": {"uv": [42, 8], "uv_size": [4, 1]},
								"south": {"uv": [24, 8], "uv_size": [8, 8]},
								"west": {"uv": [42, 8], "uv_size": [4, 1]},
								"up": {"uv": [46, 9], "uv_size": [-4, -1]},
								"down": {"uv": [46, 9], "uv_size": [-4, -1]}
							}
						},
						{
							"origin": [-11.1, 24, 4],
							"size": [7.8, 8, 1],
							"pivot": [-3.2, 24, 4],
							"rotation": [0, -90, 0],
							"uv": {
								"north": {"uv": [8, 8], "uv_size": [-8, 8]},
								"east": {"uv": [42, 8], "uv_size": [4, 1]},
								"south": {"uv": [24, 8], "uv_size": [-8, 8]},
								"west": {"uv": [42, 8], "uv_size": [4, 1]},
								"up": {"uv": [46, 9], "uv_size": [-4, -1]},
								"down": {"uv": [46, 9], "uv_size": [-4, -1]}
							}
						},
						{
							"origin": [-3.4, 26, 4],
							"size": [8, 4, 1],
							"pivot": [4.6, 26, 4],
							"rotation": [0, -90, 0],
							"uv": {
								"north": {"uv": [48, 10], "uv_size": [8, 4]},
								"east": {"uv": [48, 10], "uv_size": [1, 4]},
								"south": {"uv": [40, 10], "uv_size": [-8, 4]},
								"west": {"uv": [49, 10], "uv_size": [-1, 4]},
								"up": {"uv": [48, 11], "uv_size": [8, -1]},
								"down": {"uv": [48, 14], "uv_size": [8, -1]}
							}
						},
						{
							"origin": [-11.6, 26, 4],
							"size": [8, 4, 1],
							"pivot": [-3.6, 26, 4],
							"rotation": [0, -90, 0],
							"uv": {
								"north": {"uv": [48, 10], "uv_size": [8, 4]},
								"east": {"uv": [48, 10], "uv_size": [1, 4]},
								"south": {"uv": [40, 10], "uv_size": [-8, 4]},
								"west": {"uv": [49, 10], "uv_size": [-1, 4]},
								"up": {"uv": [48, 11], "uv_size": [8, -1]},
								"down": {"uv": [48, 14], "uv_size": [8, -1]}
							}
						},
						{
							"origin": [-1.4, 25, 2],
							"size": [6, 1, 1],
							"pivot": [4.6, 25, 2],
							"rotation": [0, -90, 0],
							"uv": {
								"north": {"uv": [48, 14], "uv_size": [6, 1]},
								"east": {"uv": [48, 10], "uv_size": [1, 4]},
								"south": {"uv": [54, 14], "uv_size": [-6, 1]},
								"west": {"uv": [54, 14], "uv_size": [-1, 1]},
								"up": {"uv": [48, 15], "uv_size": [6, -1]},
								"down": {"uv": [48, 15], "uv_size": [6, -1]}
							}
						},
						{
							"origin": [-9.6, 25, 2],
							"size": [6, 1, 1],
							"pivot": [-3.6, 25, 2],
							"rotation": [0, -90, 0],
							"uv": {
								"north": {"uv": [48, 14], "uv_size": [6, 1]},
								"east": {"uv": [48, 10], "uv_size": [1, 4]},
								"south": {"uv": [54, 14], "uv_size": [-6, 1]},
								"west": {"uv": [54, 14], "uv_size": [-1, 1]},
								"up": {"uv": [48, 15], "uv_size": [6, -1]},
								"down": {"uv": [48, 15], "uv_size": [6, -1]}
							}
						},
						{
							"origin": [0.6, 23.9, 0],
							"size": [4, 1.1, 1],
							"pivot": [4.6, 24, 0],
							"rotation": [0, -90, 0],
							"uv": {
								"north": {"uv": [48, 15], "uv_size": [4, 1]},
								"east": {"uv": [48, 15], "uv_size": [4, 1]},
								"south": {"uv": [48, 15], "uv_size": [4, 1]},
								"west": {"uv": [48, 15], "uv_size": [4, 1]},
								"up": {"uv": [52, 16], "uv_size": [-4, -1]},
								"down": {"uv": [52, 16], "uv_size": [-4, -1]}
							}
						},
						{
							"origin": [-7.6, 23.9, 0],
							"size": [4, 1.1, 1],
							"pivot": [-3.6, 24, 0],
							"rotation": [0, -90, 0],
							"uv": {
								"north": {"uv": [48, 15], "uv_size": [4, 1]},
								"east": {"uv": [48, 15], "uv_size": [4, 1]},
								"south": {"uv": [48, 15], "uv_size": [4, 1]},
								"west": {"uv": [48, 15], "uv_size": [4, 1]},
								"up": {"uv": [52, 16], "uv_size": [-4, -1]},
								"down": {"uv": [52, 16], "uv_size": [-4, -1]}
							}
						},
						{
							"origin": [-1.4, 30, 3],
							"size": [6, 1, 1],
							"pivot": [4.6, 30, 3],
							"rotation": [0, -90, 0],
							"uv": {
								"north": {"uv": [49, 9], "uv_size": [6, 1]},
								"east": {"uv": [49, 9], "uv_size": [1, 1]},
								"south": {"uv": [55, 9], "uv_size": [-6, 1]},
								"west": {"uv": [54, 9], "uv_size": [1, 1]},
								"up": {"uv": [49, 10], "uv_size": [6, -1]},
								"down": {"uv": [56, 14], "uv_size": [-8, -1]}
							}
						},
						{
							"origin": [-9.6, 30, 3],
							"size": [6, 1, 1],
							"pivot": [-3.6, 30, 3],
							"rotation": [0, -90, 0],
							"uv": {
								"north": {"uv": [49, 9], "uv_size": [6, 1]},
								"east": {"uv": [49, 9], "uv_size": [1, 1]},
								"south": {"uv": [55, 9], "uv_size": [-6, 1]},
								"west": {"uv": [54, 9], "uv_size": [1, 1]},
								"up": {"uv": [49, 10], "uv_size": [6, -1]},
								"down": {"uv": [56, 14], "uv_size": [-8, -1]}
							}
						},
						{
							"origin": [1.6, 31, 1],
							"size": [3, 1.1, 1],
							"pivot": [4.6, 31, 1],
							"rotation": [0, -90, 0],
							"uv": {
								"north": {"uv": [50, 8], "uv_size": [3, 1]},
								"east": {"uv": [49, 9], "uv_size": [1, 1]},
								"south": {"uv": [53, 8], "uv_size": [-3, 1]},
								"west": {"uv": [54, 9], "uv_size": [1, 1]},
								"up": {"uv": [50, 9], "uv_size": [3, -1]},
								"down": {"uv": [56, 14], "uv_size": [-8, -1]}
							}
						},
						{
							"origin": [-6.6, 31, 1],
							"size": [3, 1.1, 1],
							"pivot": [-3.6, 31, 1],
							"rotation": [0, -90, 0],
							"uv": {
								"north": {"uv": [50, 8], "uv_size": [3, 1]},
								"east": {"uv": [49, 9], "uv_size": [1, 1]},
								"south": {"uv": [53, 8], "uv_size": [-3, 1]},
								"west": {"uv": [54, 9], "uv_size": [1, 1]},
								"up": {"uv": [50, 9], "uv_size": [3, -1]},
								"down": {"uv": [56, 14], "uv_size": [-8, -1]}
							}
						}
					]
				},
				{
					"name": "bipedBody",
					"pivot": [0, 24, 0]
				},
				{
					"name": "armorBody",
					"parent": "bipedBody",
					"pivot": [0, 24, 0]
				},
				{
					"name": "bone3",
					"parent": "armorBody",
					"pivot": [0, 24, 0],
					"cubes": [
						{
							"origin": [-4, 12, -2],
							"size": [8, 12, 4],
							"uv": {
								"north": {"uv": [20, 20], "uv_size": [8, 12]},
								"east": {"uv": [16, 20], "uv_size": [4, 12]},
								"south": {"uv": [32, 20], "uv_size": [8, 12]},
								"west": {"uv": [28, 20], "uv_size": [4, 12]},
								"up": {"uv": [20, 16], "uv_size": [8, 4]},
								"down": {"uv": [28, 20], "uv_size": [8, -4]}
							}
						}
					]
				},
				{
					"name": "bone2",
					"parent": "bone3",
					"pivot": [0, 18, -2.3],
					"cubes": [
						{
							"origin": [-4.1, 12, -2.4],
							"size": [1, 2, 0.5],
							"uv": {
								"north": {"uv": [20, 46], "uv_size": [1, 2]},
								"east": {"uv": [20, 46], "uv_size": [1, 2]},
								"south": {"uv": [20, 46], "uv_size": [1, 2]},
								"west": {"uv": [20, 46], "uv_size": [1, 2]},
								"up": {"uv": [21, 48], "uv_size": [-1, -2]},
								"down": {"uv": [21, 48], "uv_size": [-1, -2]}
							}
						},
						{
							"origin": [-3.1, 14, -2.4],
							"size": [1.1, 2, 0.5],
							"uv": {
								"north": {"uv": [21, 44], "uv_size": [1, 2]},
								"east": {"uv": [21, 44], "uv_size": [1, 2]},
								"south": {"uv": [21, 44], "uv_size": [1, 2]},
								"west": {"uv": [21, 44], "uv_size": [1, 2]},
								"up": {"uv": [22, 46], "uv_size": [-1, -2]},
								"down": {"uv": [22, 46], "uv_size": [-1, -2]}
							}
						},
						{
							"origin": [2, 14, -2.4],
							"size": [1.1, 2, 0.5],
							"uv": {
								"north": {"uv": [21, 44], "uv_size": [1, 2]},
								"east": {"uv": [21, 44], "uv_size": [1, 2]},
								"south": {"uv": [21, 44], "uv_size": [1, 2]},
								"west": {"uv": [21, 44], "uv_size": [1, 2]},
								"up": {"uv": [22, 46], "uv_size": [-1, -2]},
								"down": {"uv": [22, 46], "uv_size": [-1, -2]}
							}
						},
						{
							"origin": [1, 15, -2.4],
							"size": [1, 1, 0.5],
							"uv": {
								"north": {"uv": [21, 44], "uv_size": [1, 2]},
								"east": {"uv": [21, 44], "uv_size": [1, 2]},
								"south": {"uv": [21, 44], "uv_size": [1, 2]},
								"west": {"uv": [21, 44], "uv_size": [1, 2]},
								"up": {"uv": [22, 46], "uv_size": [-1, -2]},
								"down": {"uv": [22, 46], "uv_size": [-1, -2]}
							}
						},
						{
							"origin": [-2, 15, -2.4],
							"size": [1, 1, 0.5],
							"uv": {
								"north": {"uv": [21, 44], "uv_size": [1, 2]},
								"east": {"uv": [21, 44], "uv_size": [1, 2]},
								"south": {"uv": [21, 44], "uv_size": [1, 2]},
								"west": {"uv": [21, 44], "uv_size": [1, 2]},
								"up": {"uv": [22, 46], "uv_size": [-1, -2]},
								"down": {"uv": [22, 46], "uv_size": [-1, -2]}
							}
						},
						{
							"origin": [3.1, 12, -2.4],
							"size": [1, 2, 0.5],
							"uv": {
								"north": {"uv": [20, 46], "uv_size": [1, 2]},
								"east": {"uv": [20, 46], "uv_size": [1, 2]},
								"south": {"uv": [20, 46], "uv_size": [1, 2]},
								"west": {"uv": [20, 46], "uv_size": [1, 2]},
								"up": {"uv": [21, 48], "uv_size": [-1, -2]},
								"down": {"uv": [21, 48], "uv_size": [-1, -2]}
							}
						},
						{
							"origin": [-4.1, 12, 2.1],
							"size": [8.2, 1, 0.5],
							"uv": {
								"north": {"uv": [32, 47], "uv_size": [8, 1]},
								"east": {"uv": [32, 47], "uv_size": [1, 1]},
								"south": {"uv": [32, 47], "uv_size": [8, 1]},
								"west": {"uv": [32, 47], "uv_size": [1, 1]},
								"up": {"uv": [40, 48], "uv_size": [-8, -1]},
								"down": {"uv": [40, 48], "uv_size": [-8, -1]}
							}
						},
						{
							"origin": [1, 13, 2.1],
							"size": [2.1, 1, 0.5],
							"uv": {
								"north": {"uv": [35, 46], "uv_size": [-3, 1]},
								"east": {"uv": [34, 46], "uv_size": [1, 1]},
								"south": {"uv": [33, 46], "uv_size": [2, 1]},
								"west": {"uv": [32, 47], "uv_size": [1, 1]},
								"up": {"uv": [35, 47], "uv_size": [-3, -1]},
								"down": {"uv": [40, 48], "uv_size": [-8, -1]}
							}
						},
						{
							"origin": [-3.1, 13, 2.1],
							"size": [2.1, 1, 0.5],
							"uv": {
								"north": {"uv": [32, 46], "uv_size": [3, 1]},
								"east": {"uv": [32, 47], "uv_size": [1, 1]},
								"south": {"uv": [37, 46], "uv_size": [2, 1]},
								"west": {"uv": [34, 46], "uv_size": [1, 1]},
								"up": {"uv": [40, 47], "uv_size": [-3, -1]},
								"down": {"uv": [40, 48], "uv_size": [-8, -1]}
							}
						},
						{
							"origin": [-1, 14, 2.1],
							"size": [2.1, 1, 0.5],
							"uv": {
								"north": {"uv": [35, 45], "uv_size": [2, 1]},
								"east": {"uv": [35, 45], "uv_size": [2, 1]},
								"south": {"uv": [35, 45], "uv_size": [2, 1]},
								"west": {"uv": [35, 45], "uv_size": [2, 1]},
								"up": {"uv": [37, 46], "uv_size": [-2, -1]},
								"down": {"uv": [37, 46], "uv_size": [-2, -1]}
							}
						},
						{
							"origin": [-4, 16, 2.1],
							"size": [8.1, 7, 0.5],
							"uv": {
								"north": {"uv": [32, 38], "uv_size": [8, 2]},
								"east": {"uv": [39, 37], "uv_size": [1, 7]},
								"south": {"uv": [32, 37], "uv_size": [8, 7]},
								"west": {"uv": [39, 37], "uv_size": [1, 7]},
								"up": {"uv": [40, 39], "uv_size": [-8, -1]},
								"down": {"uv": [40, 40], "uv_size": [-8, -1]}
							}
						},
						{
							"origin": [-3.1, 14, 2.1],
							"size": [6.2, 2, 0.5],
							"uv": {
								"north": {"uv": [35, 45], "uv_size": [2, 1]},
								"east": {"uv": [38, 44], "uv_size": [1, 1]},
								"south": {"uv": [33, 44], "uv_size": [6, 2]},
								"west": {"uv": [35, 45], "uv_size": [2, 1]},
								"up": {"uv": [39, 45], "uv_size": [-2, -1]},
								"down": {"uv": [37, 46], "uv_size": [-2, -1]}
							}
						},
						{
							"origin": [-4.1, 16, -2.4],
							"size": [8.2, 1, 0.8],
							"uv": {
								"north": {"uv": [20, 43], "uv_size": [8, 1]},
								"east": {"uv": [26, 44], "uv_size": [1, 1]},
								"south": {"uv": [27, 43], "uv_size": [-6, 2]},
								"west": {"uv": [26, 44], "uv_size": [1, 1]},
								"up": {"uv": [20, 38], "uv_size": [8, 1]},
								"down": {"uv": [28, 44], "uv_size": [-8, -1]}
							}
						},
						{
							"origin": [-3.1, 22, -2.4],
							"size": [6.2, 1, 0.5],
							"uv": {
								"north": {"uv": [21, 37], "uv_size": [6, 1]},
								"east": {"uv": [21, 37], "uv_size": [1, 1]},
								"south": {"uv": [21, 37], "uv_size": [6, 1]},
								"west": {"uv": [21, 37], "uv_size": [1, 1]},
								"up": {"uv": [27, 38], "uv_size": [-6, -1]},
								"down": {"uv": [21, 44], "uv_size": [6, 1]}
							}
						},
						{
							"origin": [1, 23, -2.4],
							"size": [2.1, 1, 0.5],
							"uv": {
								"north": {"uv": [25, 36], "uv_size": [2, 1]},
								"east": {"uv": [22, 36], "uv_size": [1, 1]},
								"south": {"uv": [22, 36], "uv_size": [1, 1]},
								"west": {"uv": [22, 36], "uv_size": [1, 1]},
								"up": {"uv": [23, 37], "uv_size": [-1, -1]},
								"down": {"uv": [21, 44], "uv_size": [6, 1]}
							}
						},
						{
							"origin": [-3.1, 23, -2.4],
							"size": [2.1, 1, 0.5],
							"uv": {
								"north": {"uv": [21, 36], "uv_size": [2, 1]},
								"east": {"uv": [22, 36], "uv_size": [1, 1]},
								"south": {"uv": [22, 36], "uv_size": [1, 1]},
								"west": {"uv": [22, 36], "uv_size": [1, 1]},
								"up": {"uv": [23, 37], "uv_size": [-1, -1]},
								"down": {"uv": [21, 44], "uv_size": [6, 1]}
							}
						},
						{
							"origin": [-4.1, 17, -2.4],
							"size": [8.2, 5, 0.5],
							"uv": {
								"north": {"uv": [20, 38], "uv_size": [8, 5]},
								"east": {"uv": [20, 38], "uv_size": [1, 5]},
								"south": {"uv": [28, 38], "uv_size": [-8, 5]},
								"west": {"uv": [27, 38], "uv_size": [1, 5]},
								"up": {"uv": [20, 38], "uv_size": [8, 1]},
								"down": {"uv": [20, 47], "uv_size": [8, 1]}
							}
						},
						{
							"origin": [4.1, 12, -1.9],
							"size": [0.5, 2, 2],
							"uv": {
								"north": {"uv": [20, 46], "uv_size": [1, 2]},
								"east": {"uv": [20, 46], "uv_size": [1, 2]},
								"south": {"uv": [20, 46], "uv_size": [1, 2]},
								"west": {"uv": [20, 46], "uv_size": [1, 2]},
								"up": {"uv": [21, 48], "uv_size": [-1, -2]},
								"down": {"uv": [21, 48], "uv_size": [-1, -2]}
							}
						},
						{
							"origin": [-4.6, 12, -1.9],
							"size": [0.5, 2, 2],
							"uv": {
								"north": {"uv": [20, 46], "uv_size": [1, 2]},
								"east": {"uv": [20, 46], "uv_size": [1, 2]},
								"south": {"uv": [20, 46], "uv_size": [1, 2]},
								"west": {"uv": [20, 46], "uv_size": [1, 2]},
								"up": {"uv": [21, 48], "uv_size": [-1, -2]},
								"down": {"uv": [21, 48], "uv_size": [-1, -2]}
							}
						},
						{
							"origin": [-4.3, 22, -0.9],
							"size": [0.5, 1, 3],
							"uv": {
								"north": {"uv": [32, 37], "uv_size": [-1, 1]},
								"east": {"uv": [33, 37], "uv_size": [-3, 1]},
								"south": {"uv": [33, 37], "uv_size": [-1, 1]},
								"west": {"uv": [30, 37], "uv_size": [3, 1]},
								"up": {"uv": [27, 40], "uv_size": [5, -2]},
								"down": {"uv": [30, 43], "uv_size": [-2, -1]}
							}
						},
						{
							"origin": [3.9, 16, -1.9],
							"size": [0.5, 6, 4],
							"uv": {
								"north": {"uv": [31, 38], "uv_size": [-4, 6]},
								"east": {"uv": [33, 38], "uv_size": [-4, 6]},
								"south": {"uv": [33, 38], "uv_size": [-1, 6]},
								"west": {"uv": [29, 38], "uv_size": [4, 6]},
								"up": {"uv": [27, 40], "uv_size": [5, -2]},
								"down": {"uv": [29, 44], "uv_size": [4, -1]}
							}
						},
						{
							"origin": [3.9, 22, -0.9],
							"size": [0.5, 1, 3],
							"uv": {
								"north": {"uv": [32, 37], "uv_size": [-1, 1]},
								"east": {"uv": [33, 37], "uv_size": [-3, 1]},
								"south": {"uv": [33, 37], "uv_size": [-1, 1]},
								"west": {"uv": [30, 37], "uv_size": [3, 1]},
								"up": {"uv": [27, 40], "uv_size": [5, -2]},
								"down": {"uv": [30, 43], "uv_size": [-2, -1]}
							}
						},
						{
							"origin": [-4.3, 16, -1.9],
							"size": [0.5, 6, 4],
							"uv": {
								"north": {"uv": [31, 38], "uv_size": [-4, 6]},
								"east": {"uv": [33, 38], "uv_size": [-4, 6]},
								"south": {"uv": [33, 38], "uv_size": [-1, 6]},
								"west": {"uv": [29, 38], "uv_size": [4, 6]},
								"up": {"uv": [27, 40], "uv_size": [5, -2]},
								"down": {"uv": [29, 44], "uv_size": [4, -1]}
							}
						}
					]
				},
				{
					"name": "bipedRightArm",
					"pivot": [-5, 22, 0]
				},
				{
					"name": "armorRightArm",
					"parent": "bipedRightArm",
					"pivot": [-5, 22, 0]
				},
				{
					"name": "bone4",
					"parent": "armorRightArm",
					"pivot": [-5, 22, 0],
					"cubes": [
						{
							"origin": [-8.1, 11.9, -2.1],
							"size": [4.2, 12.1, 4.2],
							"uv": {
								"north": {"uv": [44, 20], "uv_size": [4, 12]},
								"east": {"uv": [40, 20], "uv_size": [4, 12]},
								"south": {"uv": [52, 20], "uv_size": [4, 12]},
								"west": {"uv": [48, 20], "uv_size": [4, 12]},
								"up": {"uv": [44, 20], "uv_size": [4, -4]},
								"down": {"uv": [52, 20], "uv_size": [-4, -4]}
							}
						}
					]
				},
				{
					"name": "armorRightOut",
					"parent": "bone4",
					"pivot": [7.1, 24.1, 2],
					"cubes": [
						{
							"origin": [-8.45, 19, -2.25],
							"size": [0.35, 4, 4.5],
							"uv": {
								"north": {"uv": [60, 53], "uv_size": [-4, 4]},
								"east": {"uv": [60, 53], "uv_size": [-4, 4]},
								"south": {"uv": [60, 53], "uv_size": [-4, 4]},
								"west": {"uv": [56, 53], "uv_size": [4, 5]},
								"up": {"uv": [56, 57], "uv_size": [1, -4]},
								"down": {"uv": [56, 57], "uv_size": [4, -1]}
							}
						},
						{
							"origin": [-3.85, 21, -2.25],
							"size": [0.35, 3, 4.5],
							"uv": {
								"north": {"uv": [48, 52], "uv_size": [1, 3]},
								"east": {"uv": [48, 52], "uv_size": [4, 3]},
								"south": {"uv": [48, 52], "uv_size": [1, 3]},
								"west": {"uv": [48, 52], "uv_size": [4, 3]},
								"up": {"uv": [52, 53], "uv_size": [-4, -1]},
								"down": {"uv": [52, 55], "uv_size": [-4, -1]}
							}
						},
						{
							"origin": [-8.45, 16, -2.25],
							"size": [0.35, 2, 4.5],
							"uv": {
								"north": {"uv": [59, 58], "uv_size": [-1, 1]},
								"east": {"uv": [60, 58], "uv_size": [-4, 2]},
								"south": {"uv": [60, 58], "uv_size": [-1, 1]},
								"west": {"uv": [57, 58], "uv_size": [3, 1]},
								"up": {"uv": [60, 59], "uv_size": [-1, -1]},
								"down": {"uv": [60, 59], "uv_size": [-1, -1]}
							}
						},
						{
							"origin": [-3.95, 17, -2.25],
							"size": [0.35, 1, 4.5],
							"uv": {
								"north": {"uv": [61, 59], "uv_size": [-1, 1]},
								"east": {"uv": [61, 59], "uv_size": [-1, 1]},
								"south": {"uv": [61, 59], "uv_size": [-1, 1]},
								"west": {"uv": [61, 59], "uv_size": [-1, 1]},
								"up": {"uv": [60, 60], "uv_size": [1, -1]},
								"down": {"uv": [60, 60], "uv_size": [1, -1]}
							}
						},
						{
							"origin": [-7.25, 23, 2.65],
							"size": [0.35, 1, 1.1],
							"pivot": [-7.25, 23, 2.45],
							"rotation": [0, 90, 0],
							"uv": {
								"north": {"uv": [63, 52], "uv_size": [-2, 1]},
								"east": {"uv": [63, 52], "uv_size": [-2, 1]},
								"south": {"uv": [63, 52], "uv_size": [-2, 1]},
								"west": {"uv": [63, 52], "uv_size": [-2, 1]},
								"up": {"uv": [61, 53], "uv_size": [2, -1]},
								"down": {"uv": [61, 53], "uv_size": [2, -1]}
							}
						},
						{
							"origin": [-8.35, 19, 2.55],
							"size": [0.35, 4, 2.4],
							"pivot": [-8.35, 19, 2.45],
							"rotation": [0, 90, 0],
							"uv": {
								"north": {"uv": [61, 55], "uv_size": [-1, 2]},
								"east": {"uv": [62, 53], "uv_size": [-2, 4]},
								"south": {"uv": [64, 59], "uv_size": [-1, 1]},
								"west": {"uv": [60, 55], "uv_size": [3, 2]},
								"up": {"uv": [60, 57], "uv_size": [2, -4]},
								"down": {"uv": [61, 56], "uv_size": [2, -1]}
							}
						},
						{
							"origin": [-8.35, 20, 4.85],
							"size": [0.35, 4, 2.1],
							"pivot": [-8.35, 19, 2.45],
							"rotation": [0, 90, 0],
							"uv": {
								"north": {"uv": [61, 55], "uv_size": [-1, 2]},
								"east": {"uv": [64, 52], "uv_size": [-2, 4]},
								"south": {"uv": [64, 59], "uv_size": [-1, 1]},
								"west": {"uv": [64, 52], "uv_size": [-2, 4]},
								"up": {"uv": [63, 60], "uv_size": [1, -1]},
								"down": {"uv": [61, 56], "uv_size": [2, -1]}
							}
						},
						{
							"origin": [-8.35, 17, 2.55],
							"size": [0.35, 1, 4.5],
							"pivot": [-8.35, 17, 2.45],
							"rotation": [0, 90, 0],
							"uv": {
								"north": {"uv": [61, 59], "uv_size": [-1, 1]},
								"east": {"uv": [61, 59], "uv_size": [-1, 1]},
								"south": {"uv": [61, 59], "uv_size": [-1, 1]},
								"west": {"uv": [61, 59], "uv_size": [-1, 1]},
								"up": {"uv": [60, 60], "uv_size": [1, -1]},
								"down": {"uv": [60, 60], "uv_size": [1, -1]}
							}
						},
						{
							"origin": [-7.35, 23, -2.05],
							"size": [0.35, 1, 3.4],
							"pivot": [-7.25, 23, -2.15],
							"rotation": [0, 90, 0],
							"uv": {
								"north": {"uv": [55, 52], "uv_size": [-1, 1]},
								"east": {"uv": [55, 52], "uv_size": [-2, 1]},
								"south": {"uv": [54, 52], "uv_size": [-1, 1]},
								"west": {"uv": [55, 52], "uv_size": [-3, 1]},
								"up": {"uv": [53, 53], "uv_size": [1, -1]},
								"down": {"uv": [53, 53], "uv_size": [1, -1]}
							}
						},
						{
							"origin": [-5.25, 17, -5.25],
							"size": [0.35, 1, 4.5],
							"pivot": [-5.15, 16, -2.15],
							"rotation": [0, 90, 0],
							"uv": {
								"north": {"uv": [52, 58], "uv_size": [-4, 1]},
								"east": {"uv": [61, 59], "uv_size": [-1, 1]},
								"south": {"uv": [61, 59], "uv_size": [-1, 1]},
								"west": {"uv": [61, 59], "uv_size": [-1, 1]},
								"up": {"uv": [60, 60], "uv_size": [1, -1]},
								"down": {"uv": [60, 60], "uv_size": [1, -1]}
							}
						},
						{
							"origin": [-8.45, 21, -2.05],
							"size": [0.35, 2, 4.5],
							"pivot": [-8.35, 22, -2.15],
							"rotation": [0, 90, 0],
							"uv": {
								"north": {"uv": [55, 52], "uv_size": [-1, 1]},
								"east": {"uv": [52, 53], "uv_size": [4, 2]},
								"south": {"uv": [54, 52], "uv_size": [-1, 1]},
								"west": {"uv": [56, 53], "uv_size": [-4, 2]},
								"up": {"uv": [53, 53], "uv_size": [1, -1]},
								"down": {"uv": [53, 53], "uv_size": [1, -1]}
							}
						},
						{
							"origin": [-8.45, 20, -2.05],
							"size": [0.35, 1, 3.4],
							"pivot": [-8.35, 21, -2.15],
							"rotation": [0, 90, 0],
							"uv": {
								"north": {"uv": [55, 52], "uv_size": [-1, 1]},
								"east": {"uv": [52, 53], "uv_size": [4, 2]},
								"south": {"uv": [54, 52], "uv_size": [-1, 1]},
								"west": {"uv": [56, 55], "uv_size": [-3, 1]},
								"up": {"uv": [53, 53], "uv_size": [1, -1]},
								"down": {"uv": [53, 53], "uv_size": [1, -1]}
							}
						},
						{
							"origin": [-8.45, 18.9, -2.05],
							"size": [0.35, 1.1, 2.5],
							"pivot": [-8.35, 19, -2.15],
							"rotation": [0, 90, 0],
							"uv": {
								"north": {"uv": [56, 56], "uv_size": [-2, 1]},
								"east": {"uv": [56, 56], "uv_size": [-2, 1]},
								"south": {"uv": [56, 56], "uv_size": [-2, 1]},
								"west": {"uv": [56, 56], "uv_size": [-2, 1]},
								"up": {"uv": [54, 57], "uv_size": [2, -1]},
								"down": {"uv": [54, 57], "uv_size": [2, -1]}
							}
						},
						{
							"origin": [-8.45, 13.9, -2.05],
							"size": [0.35, 1.1, 4.5],
							"pivot": [-8.35, 15, -2.15],
							"rotation": [0, 90, 0],
							"uv": {
								"north": {"uv": [56, 61], "uv_size": [-4, 1]},
								"east": {"uv": [52, 61], "uv_size": [4, 1]},
								"south": {"uv": [56, 61], "uv_size": [-4, 1]},
								"west": {"uv": [56, 61], "uv_size": [-4, 1]},
								"up": {"uv": [52, 62], "uv_size": [2, -1]},
								"down": {"uv": [52, 62], "uv_size": [2, -1]}
							}
						},
						{
							"origin": [-8.45, 13.9, 2.45],
							"size": [0.35, 1.1, 4.5],
							"pivot": [-8.35, 15, 2.35],
							"rotation": [0, 90, 0],
							"uv": {
								"north": {"uv": [56, 61], "uv_size": [-4, 1]},
								"east": {"uv": [52, 61], "uv_size": [4, 1]},
								"south": {"uv": [56, 61], "uv_size": [-4, 1]},
								"west": {"uv": [56, 61], "uv_size": [-4, 1]},
								"up": {"uv": [52, 62], "uv_size": [2, -1]},
								"down": {"uv": [52, 62], "uv_size": [2, -1]}
							}
						},
						{
							"origin": [-8.45, 13.9, -2.25],
							"size": [0.35, 1.1, 4.5],
							"uv": {
								"north": {"uv": [60, 61], "uv_size": [-4, 1]},
								"east": {"uv": [58, 61], "uv_size": [-4, 1]},
								"south": {"uv": [60, 61], "uv_size": [-4, 1]},
								"west": {"uv": [60, 61], "uv_size": [-4, 1]},
								"up": {"uv": [56, 62], "uv_size": [4, -1]},
								"down": {"uv": [56, 62], "uv_size": [4, -1]}
							}
						},
						{
							"origin": [-3.95, 13.9, -2.25],
							"size": [0.35, 1.1, 4.5],
							"uv": {
								"north": {"uv": [49, 61], "uv_size": [4, 1]},
								"east": {"uv": [49, 61], "uv_size": [4, 1]},
								"south": {"uv": [49, 61], "uv_size": [4, 1]},
								"west": {"uv": [49, 61], "uv_size": [4, 1]},
								"up": {"uv": [53, 62], "uv_size": [-4, -1]},
								"down": {"uv": [53, 62], "uv_size": [-4, -1]}
							}
						},
						{
							"origin": [-7.1, 24, -2.3],
							"size": [3.3, 0.2, 4.5],
							"uv": {
								"north": {"uv": [55, 48], "uv_size": [-2, 1]},
								"east": {"uv": [54, 49], "uv_size": [1, 2]},
								"south": {"uv": [53, 48], "uv_size": [2, 1]},
								"west": {"uv": [54, 49], "uv_size": [1, 2]},
								"up": {"uv": [55, 52], "uv_size": [-3, -4]},
								"down": {"uv": [55, 52], "uv_size": [-2, -4]}
							}
						},
						{
							"origin": [-8.2, 24, -1.3],
							"size": [1.1, 0.2, 2.5],
							"uv": {
								"north": {"uv": [55, 49], "uv_size": [1, 2]},
								"east": {"uv": [55, 49], "uv_size": [1, 2]},
								"south": {"uv": [55, 49], "uv_size": [1, 2]},
								"west": {"uv": [55, 49], "uv_size": [1, 2]},
								"up": {"uv": [56, 51], "uv_size": [-1, -2]},
								"down": {"uv": [56, 51], "uv_size": [-1, -2]}
							}
						}
					]
				},
				{
					"name": "bipedLeftArm",
					"pivot": [5, 22, 0]
				},
				{
					"name": "armorLeftArm",
					"parent": "bipedLeftArm",
					"pivot": [5, 22, 0]
				},
				{
					"name": "bone8",
					"parent": "armorLeftArm",
					"pivot": [5, 22, 0],
					"cubes": [
						{
							"origin": [3.9, 11.9, -2.1],
							"size": [4.2, 12.2, 4.2],
							"uv": {
								"north": {"uv": [36, 52], "uv_size": [4, 12]},
								"east": {"uv": [32, 52], "uv_size": [4, 12]},
								"south": {"uv": [44, 52], "uv_size": [4, 12]},
								"west": {"uv": [40, 52], "uv_size": [4, 12]},
								"up": {"uv": [36, 48], "uv_size": [4, 4]},
								"down": {"uv": [40, 52], "uv_size": [4, -4]}
							}
						}
					]
				},
				{
					"name": "launcher",
					"parent": "bone8",
					"pivot": [6, 24, 0],
					"cubes": [
						{
							"origin": [6.5, 23.2, 1],
							"size": [1, 4, 1],
							"pivot": [7.5, 23.2, 1],
							"rotation": [-47.5, 0, 0],
							"uv": {
								"north": {"uv": [0, 5], "uv_size": [1, 1]},
								"east": {"uv": [0, 5], "uv_size": [1, 1]},
								"south": {"uv": [0, 5], "uv_size": [1, 1]},
								"west": {"uv": [0, 5], "uv_size": [1, 1]},
								"up": {"uv": [1, 6], "uv_size": [-1, -1]},
								"down": {"uv": [1, 6], "uv_size": [-1, -1]}
							}
						},
						{
							"origin": [6.5, 25.3, 4.1],
							"size": [1, 2, 1],
							"pivot": [7.5, 25.3, 4.1],
							"rotation": [55, 0, 0],
							"uv": {
								"north": {"uv": [0, 5], "uv_size": [1, 1]},
								"east": {"uv": [0, 5], "uv_size": [1, 1]},
								"south": {"uv": [0, 5], "uv_size": [1, 1]},
								"west": {"uv": [0, 5], "uv_size": [1, 1]},
								"up": {"uv": [3, 6], "uv_size": [-1, -1]},
								"down": {"uv": [1, 6], "uv_size": [-1, -1]}
							}
						},
						{
							"origin": [6.5, 25.1, 3.7],
							"size": [1, 1, 1],
							"uv": {
								"north": {"uv": [0, 5], "uv_size": [1, 1]},
								"east": {"uv": [0, 5], "uv_size": [1, 1]},
								"south": {"uv": [0, 5], "uv_size": [1, 1]},
								"west": {"uv": [0, 5], "uv_size": [1, 1]},
								"up": {"uv": [1, 6], "uv_size": [-1, -1]},
								"down": {"uv": [1, 6], "uv_size": [-1, -1]}
							}
						}
					]
				},
				{
					"name": "bone",
					"parent": "launcher",
					"pivot": [7, 27, 3.2],
					"cubes": [
						{
							"origin": [7.5, 26.7, -0.8],
							"size": [0.5, 0.6, 4],
							"uv": {
								"north": {"uv": [58, 12], "uv_size": [1, 1]},
								"east": {"uv": [2, 5], "uv_size": [1, 1]},
								"south": {"uv": [58, 12], "uv_size": [1, 1]},
								"west": {"uv": [5, 5], "uv_size": [1, 1]},
								"up": {"uv": [6, 6], "uv_size": [-1, -1]},
								"down": {"uv": [59, 13], "uv_size": [-1, -1]}
							}
						},
						{
							"origin": [6, 26.7, -0.8],
							"size": [0.5, 0.6, 4],
							"uv": {
								"north": {"uv": [58, 12], "uv_size": [1, 1]},
								"east": {"uv": [5, 5], "uv_size": [1, 1]},
								"south": {"uv": [58, 12], "uv_size": [1, 1]},
								"west": {"uv": [2, 5], "uv_size": [1, 1]},
								"up": {"uv": [6, 6], "uv_size": [-1, -1]},
								"down": {"uv": [59, 13], "uv_size": [-1, -1]}
							}
						},
						{
							"origin": [6.4, 27.3, -0.8],
							"size": [1.2, 0.7, 4],
							"uv": {
								"north": {"uv": [58, 12], "uv_size": [1, 1]},
								"east": {"uv": [58, 12], "uv_size": [1, 1]},
								"south": {"uv": [58, 12], "uv_size": [1, 1]},
								"west": {"uv": [58, 12], "uv_size": [1, 1]},
								"up": {"uv": [6, 6], "uv_size": [-1, -1]},
								"down": {"uv": [3, 6], "uv_size": [-1, -1]}
							}
						},
						{
							"origin": [5.9, 27, -0.8],
							"size": [0.5, 0.7, 4],
							"pivot": [6.4, 27, -0.8],
							"rotation": [0, 0, 36],
							"uv": {
								"north": {"uv": [58, 12], "uv_size": [1, 1]},
								"east": {"uv": [58, 12], "uv_size": [1, 1]},
								"south": {"uv": [58, 12], "uv_size": [1, 1]},
								"west": {"uv": [2, 5], "uv_size": [1, 1]},
								"up": {"uv": [6, 6], "uv_size": [-1, -1]},
								"down": {"uv": [3, 6], "uv_size": [-1, -1]}
							}
						},
						{
							"origin": [7.6, 27, -0.8],
							"size": [0.5, 0.7, 4],
							"pivot": [7.6, 27, -0.8],
							"rotation": [0, 0, -36],
							"uv": {
								"north": {"uv": [59, 12], "uv_size": [-1, 1]},
								"east": {"uv": [2, 5], "uv_size": [1, 1]},
								"south": {"uv": [59, 12], "uv_size": [-1, 1]},
								"west": {"uv": [59, 12], "uv_size": [-1, 1]},
								"up": {"uv": [5, 6], "uv_size": [1, -1]},
								"down": {"uv": [2, 6], "uv_size": [1, -1]}
							}
						},
						{
							"origin": [6.5, 26.1, -0.8],
							"size": [1, 0.4, 4],
							"uv": {
								"north": {"uv": [58, 12], "uv_size": [1, 1]},
								"east": {"uv": [58, 12], "uv_size": [1, 1]},
								"south": {"uv": [58, 12], "uv_size": [1, 1]},
								"west": {"uv": [58, 12], "uv_size": [1, 1]},
								"up": {"uv": [3, 6], "uv_size": [-1, -1]},
								"down": {"uv": [59, 13], "uv_size": [-1, -1]}
							}
						},
						{
							"origin": [6.8, 25.7, -0.8],
							"size": [0.4, 0.2, 4],
							"uv": {
								"north": {"uv": [58, 12], "uv_size": [1, 1]},
								"east": {"uv": [58, 12], "uv_size": [1, 1]},
								"south": {"uv": [58, 12], "uv_size": [1, 1]},
								"west": {"uv": [58, 12], "uv_size": [1, 1]},
								"up": {"uv": [3, 6], "uv_size": [-1, -1]},
								"down": {"uv": [59, 13], "uv_size": [-1, -1]}
							}
						},
						{
							"origin": [7.2, 26.2, -0.8],
							"size": [0.3, 0.7, 4],
							"pivot": [7.5, 26.2, -0.8],
							"rotation": [0, 0, 39],
							"uv": {
								"north": {"uv": [58, 12], "uv_size": [1, 1]},
								"east": {"uv": [2, 5], "uv_size": [1, 1]},
								"south": {"uv": [58, 12], "uv_size": [1, 1]},
								"west": {"uv": [58, 12], "uv_size": [1, 1]},
								"up": {"uv": [3, 6], "uv_size": [-1, -1]},
								"down": {"uv": [59, 13], "uv_size": [-1, -1]}
							}
						},
						{
							"origin": [7, 25.8, -0.8],
							"size": [0.2, 0.4, 4],
							"pivot": [7.2, 25.8, -0.8],
							"rotation": [0, 0, 39],
							"uv": {
								"north": {"uv": [58, 12], "uv_size": [1, 1]},
								"east": {"uv": [2, 5], "uv_size": [1, 1]},
								"south": {"uv": [58, 12], "uv_size": [1, 1]},
								"west": {"uv": [58, 12], "uv_size": [1, 1]},
								"up": {"uv": [3, 6], "uv_size": [-1, -1]},
								"down": {"uv": [2, 6], "uv_size": [1, -1]}
							}
						},
						{
							"origin": [6.8, 25.8, -0.8],
							"size": [0.2, 0.4, 4],
							"pivot": [6.8, 25.8, -0.8],
							"rotation": [0, 0, -39],
							"uv": {
								"north": {"uv": [59, 12], "uv_size": [-1, 1]},
								"east": {"uv": [59, 12], "uv_size": [-1, 1]},
								"south": {"uv": [59, 12], "uv_size": [-1, 1]},
								"west": {"uv": [3, 5], "uv_size": [-1, 1]},
								"up": {"uv": [2, 6], "uv_size": [1, -1]},
								"down": {"uv": [2, 6], "uv_size": [1, -1]}
							}
						},
						{
							"origin": [6.5, 26.4, -0.8],
							"size": [0.3, 0.7, 4],
							"pivot": [6.8, 26.4, -0.8],
							"rotation": [0, 0, -38.5],
							"uv": {
								"north": {"uv": [58, 12], "uv_size": [1, 1]},
								"east": {"uv": [58, 12], "uv_size": [1, 1]},
								"south": {"uv": [58, 12], "uv_size": [1, 1]},
								"west": {"uv": [2, 5], "uv_size": [1, 1]},
								"up": {"uv": [3, 6], "uv_size": [-1, -1]},
								"down": {"uv": [59, 13], "uv_size": [-1, -1]}
							}
						}
					]
				},
				{
					"name": "doomblade",
					"parent": "bone8",
					"pivot": [8.2, 14.8, 0],
					"rotation": [90, 180, 90]
				},
				{
					"name": "group",
					"parent": "doomblade",
					"pivot": [-16.2, 16.65, 16.5],
					"cubes": [
						{
							"origin": [4.465, 14.05, 6.15],
							"size": [0.45, 1.5, 0.9],
							"pivot": [-8.3, 9.55, -6.75],
							"rotation": [0, 22.5, 0],
							"uv": {
								"north": {"uv": [11, 3], "uv_size": [1, 1]},
								"east": {"uv": [11, 3], "uv_size": [1, 1]},
								"south": {"uv": [11, 3], "uv_size": [1, 1]},
								"west": {"uv": [11, 3], "uv_size": [1, 1]},
								"up": {"uv": [12, 4], "uv_size": [-1, -1]},
								"down": {"uv": [12, 4], "uv_size": [-1, -1]}
							}
						},
						{
							"origin": [8.95, 14.05, 0.375],
							"size": [0.75, 1.5, 1.125],
							"uv": {
								"north": {"uv": [11, 3], "uv_size": [1, 1]},
								"east": {"uv": [11, 3], "uv_size": [1, 1]},
								"south": {"uv": [11, 3], "uv_size": [1, 1]},
								"west": {"uv": [11, 3], "uv_size": [1, 1]},
								"up": {"uv": [12, 4], "uv_size": [-1, -1]},
								"down": {"uv": [12, 4], "uv_size": [-1, -1]}
							}
						},
						{
							"origin": [14.2, 14.05, 5.025],
							"size": [0.75, 1.5, 0.57],
							"pivot": [1.45, 9.55, 17.7],
							"rotation": [0, 22.5, 0],
							"uv": {
								"north": {"uv": [11, 3], "uv_size": [1, 1]},
								"east": {"uv": [11, 3], "uv_size": [1, 1]},
								"south": {"uv": [11, 3], "uv_size": [1, 1]},
								"west": {"uv": [11, 3], "uv_size": [1, 1]},
								"up": {"uv": [12, 4], "uv_size": [-1, -1]},
								"down": {"uv": [12, 4], "uv_size": [-1, -1]}
							}
						},
						{
							"origin": [9.7, 14.05, 0.375],
							"size": [0.75, 1.5, 0.75],
							"uv": {
								"north": {"uv": [11, 3], "uv_size": [1, 1]},
								"east": {"uv": [11, 3], "uv_size": [1, 1]},
								"south": {"uv": [11, 3], "uv_size": [1, 1]},
								"west": {"uv": [11, 3], "uv_size": [1, 1]},
								"up": {"uv": [12, 4], "uv_size": [-1, -1]},
								"down": {"uv": [12, 4], "uv_size": [-1, -1]}
							}
						},
						{
							"origin": [5.05, 14.05, 0.375],
							"size": [0.45, 1.5, 1.125],
							"uv": {
								"north": {"uv": [11, 3], "uv_size": [1, 1]},
								"east": {"uv": [11, 3], "uv_size": [1, 1]},
								"south": {"uv": [11, 3], "uv_size": [1, 1]},
								"west": {"uv": [11, 3], "uv_size": [1, 1]},
								"up": {"uv": [12, 4], "uv_size": [-1, -1]},
								"down": {"uv": [12, 4], "uv_size": [-1, -1]}
							}
						},
						{
							"origin": [1.135, 14.05, -4.125],
							"size": [0.465, 1.5, 1.125],
							"pivot": [-7.55, 9.55, 9],
							"rotation": [0, -22.5, 0],
							"uv": {
								"north": {"uv": [11, 3], "uv_size": [1, 1]},
								"east": {"uv": [11, 3], "uv_size": [1, 1]},
								"south": {"uv": [11, 3], "uv_size": [1, 1]},
								"west": {"uv": [11, 3], "uv_size": [1, 1]},
								"up": {"uv": [12, 4], "uv_size": [-1, -1]},
								"down": {"uv": [12, 4], "uv_size": [-1, -1]}
							}
						},
						{
							"origin": [5.05, 14.05, 0],
							"size": [5.25, 1.5, 0.375],
							"uv": {
								"north": {"uv": [11, 3], "uv_size": [1, 1]},
								"east": {"uv": [11, 3], "uv_size": [1, 1]},
								"south": {"uv": [11, 3], "uv_size": [1, 1]},
								"west": {"uv": [11, 3], "uv_size": [1, 1]},
								"up": {"uv": [12, 4], "uv_size": [-1, -1]},
								"down": {"uv": [12, 4], "uv_size": [-1, -1]}
							}
						},
						{
							"origin": [5.2, 14.2, 0.375],
							"size": [3.75, 1.2, 0.9],
							"uv": {
								"north": {"uv": [58, 12], "uv_size": [3, 1]},
								"east": {"uv": [58, 12], "uv_size": [3, 1]},
								"south": {"uv": [58, 12], "uv_size": [3, 1]},
								"west": {"uv": [58, 12], "uv_size": [3, 1]},
								"up": {"uv": [61, 13], "uv_size": [-3, -1]},
								"down": {"uv": [61, 13], "uv_size": [-3, -1]}
							}
						}
					]
				},
				{
					"name": "group2",
					"parent": "doomblade",
					"pivot": [-16.2, 16.65, 16.5],
					"cubes": [
						{
							"origin": [4, 15.565, -6.375],
							"size": [0.15, 0.015, 0.375],
							"pivot": [-10.1, 9.55, 6.75],
							"rotation": [0, -22.5, 0],
							"uv": {
								"north": {"uv": [2, 5], "uv_size": [1, 1]},
								"east": {"uv": [2, 5], "uv_size": [1, 1]},
								"south": {"uv": [2, 5], "uv_size": [1, 1]},
								"west": {"uv": [2, 5], "uv_size": [1, 1]},
								"up": {"uv": [3, 6], "uv_size": [-1, -1]},
								"down": {"uv": [3, 6], "uv_size": [-1, -1]}
							}
						},
						{
							"origin": [4.225, 15.565, -6.375],
							"size": [0.15, 0.015, 0.375],
							"pivot": [-9.875, 9.55, 6.75],
							"rotation": [0, -22.5, 0],
							"uv": {
								"north": {"uv": [2, 5], "uv_size": [1, 1]},
								"east": {"uv": [2, 5], "uv_size": [1, 1]},
								"south": {"uv": [2, 5], "uv_size": [1, 1]},
								"west": {"uv": [2, 5], "uv_size": [1, 1]},
								"up": {"uv": [3, 6], "uv_size": [-1, -1]},
								"down": {"uv": [3, 6], "uv_size": [-1, -1]}
							}
						},
						{
							"origin": [4.45, 15.565, -6.375],
							"size": [0.15, 0.015, 0.375],
							"pivot": [-9.65, 9.55, 6.75],
							"rotation": [0, -22.5, 0],
							"uv": {
								"north": {"uv": [2, 5], "uv_size": [1, 1]},
								"east": {"uv": [2, 5], "uv_size": [1, 1]},
								"south": {"uv": [2, 5], "uv_size": [1, 1]},
								"west": {"uv": [2, 5], "uv_size": [1, 1]},
								"up": {"uv": [3, 6], "uv_size": [-1, -1]},
								"down": {"uv": [3, 6], "uv_size": [-1, -1]}
							}
						},
						{
							"origin": [4.675, 15.565, -6.375],
							"size": [0.15, 0.015, 0.375],
							"pivot": [-9.425, 9.55, 6.75],
							"rotation": [0, -22.5, 0],
							"uv": {
								"north": {"uv": [2, 5], "uv_size": [1, 1]},
								"east": {"uv": [2, 5], "uv_size": [1, 1]},
								"south": {"uv": [2, 5], "uv_size": [1, 1]},
								"west": {"uv": [2, 5], "uv_size": [1, 1]},
								"up": {"uv": [3, 6], "uv_size": [-1, -1]},
								"down": {"uv": [3, 6], "uv_size": [-1, -1]}
							}
						}
					]
				},
				{
					"name": "group3",
					"parent": "doomblade",
					"pivot": [-16.2, 16.65, 16.5],
					"cubes": [
						{
							"origin": [4, 14.035, -6.375],
							"size": [0.15, 0.015, 0.375],
							"pivot": [-10.1, 9.55, 6.75],
							"rotation": [0, -22.5, 0],
							"uv": {
								"north": {"uv": [2, 5], "uv_size": [1, 1]},
								"east": {"uv": [2, 5], "uv_size": [1, 1]},
								"south": {"uv": [2, 5], "uv_size": [1, 1]},
								"west": {"uv": [2, 5], "uv_size": [1, 1]},
								"up": {"uv": [3, 6], "uv_size": [-1, -1]},
								"down": {"uv": [3, 6], "uv_size": [-1, -1]}
							}
						},
						{
							"origin": [4.225, 14.035, -6.375],
							"size": [0.15, 0.015, 0.375],
							"pivot": [-9.875, 9.55, 6.75],
							"rotation": [0, -22.5, 0],
							"uv": {
								"north": {"uv": [2, 5], "uv_size": [1, 1]},
								"east": {"uv": [2, 5], "uv_size": [1, 1]},
								"south": {"uv": [2, 5], "uv_size": [1, 1]},
								"west": {"uv": [2, 5], "uv_size": [1, 1]},
								"up": {"uv": [3, 6], "uv_size": [-1, -1]},
								"down": {"uv": [3, 6], "uv_size": [-1, -1]}
							}
						},
						{
							"origin": [4.45, 14.035, -6.375],
							"size": [0.15, 0.015, 0.375],
							"pivot": [-9.65, 9.55, 6.75],
							"rotation": [0, -22.5, 0],
							"uv": {
								"north": {"uv": [2, 5], "uv_size": [1, 1]},
								"east": {"uv": [2, 5], "uv_size": [1, 1]},
								"south": {"uv": [2, 5], "uv_size": [1, 1]},
								"west": {"uv": [2, 5], "uv_size": [1, 1]},
								"up": {"uv": [3, 6], "uv_size": [-1, -1]},
								"down": {"uv": [3, 6], "uv_size": [-1, -1]}
							}
						},
						{
							"origin": [4.675, 14.035, -6.375],
							"size": [0.15, 0.015, 0.375],
							"pivot": [-9.425, 9.55, 6.75],
							"rotation": [0, -22.5, 0],
							"uv": {
								"north": {"uv": [2, 5], "uv_size": [1, 1]},
								"east": {"uv": [2, 5], "uv_size": [1, 1]},
								"south": {"uv": [2, 5], "uv_size": [1, 1]},
								"west": {"uv": [2, 5], "uv_size": [1, 1]},
								"up": {"uv": [3, 6], "uv_size": [-1, -1]},
								"down": {"uv": [3, 6], "uv_size": [-1, -1]}
							}
						}
					]
				},
				{
					"name": "blade",
					"parent": "doomblade",
					"pivot": [4.8, 14.85, 0.7],
					"cubes": [
						{
							"origin": [14.05, 14.6125, -4.425],
							"size": [0.375, 0.375, 1.5],
							"pivot": [3.325, 27.55, -15.075],
							"rotation": [0, -45, 0],
							"uv": {
								"north": {"uv": [5, 5], "uv_size": [1, 1]},
								"east": {"uv": [5, 5], "uv_size": [1, 1]},
								"south": {"uv": [5, 5], "uv_size": [1, 1]},
								"west": {"uv": [5, 5], "uv_size": [1, 1]},
								"up": {"uv": [6, 6], "uv_size": [-1, -1]},
								"down": {"uv": [6, 6], "uv_size": [-1, -1]}
							}
						},
						{
							"origin": [11.05, 14.6125, -4.425],
							"size": [0.375, 0.375, 1.5],
							"pivot": [0.325, 27.55, -15.075],
							"rotation": [0, -45, 0],
							"uv": {
								"north": {"uv": [5, 5], "uv_size": [1, 1]},
								"east": {"uv": [5, 5], "uv_size": [1, 1]},
								"south": {"uv": [5, 5], "uv_size": [1, 1]},
								"west": {"uv": [5, 5], "uv_size": [1, 1]},
								"up": {"uv": [6, 6], "uv_size": [-1, -1]},
								"down": {"uv": [6, 6], "uv_size": [-1, -1]}
							}
						},
						{
							"origin": [12.55, 14.6125, -4.425],
							"size": [0.375, 0.375, 1.5],
							"pivot": [1.825, 27.55, -15.075],
							"rotation": [0, -45, 0],
							"uv": {
								"north": {"uv": [5, 5], "uv_size": [1, 1]},
								"east": {"uv": [5, 5], "uv_size": [1, 1]},
								"south": {"uv": [5, 5], "uv_size": [1, 1]},
								"west": {"uv": [5, 5], "uv_size": [1, 1]},
								"up": {"uv": [6, 6], "uv_size": [-1, -1]},
								"down": {"uv": [6, 6], "uv_size": [-1, -1]}
							}
						},
						{
							"origin": [15.55, 14.6125, -4.425],
							"size": [0.375, 0.375, 1.5],
							"pivot": [4.825, 27.55, -15.075],
							"rotation": [0, -45, 0],
							"uv": {
								"north": {"uv": [5, 5], "uv_size": [1, 1]},
								"east": {"uv": [5, 5], "uv_size": [1, 1]},
								"south": {"uv": [5, 5], "uv_size": [1, 1]},
								"west": {"uv": [5, 5], "uv_size": [1, 1]},
								"up": {"uv": [6, 6], "uv_size": [-1, -1]},
								"down": {"uv": [6, 6], "uv_size": [-1, -1]}
							}
						},
						{
							"origin": [9.8275, 14.65, -4.2],
							"size": [0.675, 0.3, 0.675],
							"pivot": [-0.8, 27.55, -15],
							"rotation": [0, -45, 0],
							"uv": {
								"north": {"uv": [0, 5], "uv_size": [1, 1]},
								"east": {"uv": [0, 5], "uv_size": [1, 1]},
								"south": {"uv": [0, 5], "uv_size": [1, 1]},
								"west": {"uv": [0, 5], "uv_size": [1, 1]},
								"up": {"uv": [1, 6], "uv_size": [-1, -1]},
								"down": {"uv": [1, 6], "uv_size": [-1, -1]}
							}
						},
						{
							"origin": [-0.95, 14.75, 0.15],
							"size": [6, 0.1, 0.975],
							"uv": {
								"north": {"uv": [0, 5], "uv_size": [1, 1]},
								"east": {"uv": [0, 5], "uv_size": [1, 1]},
								"south": {"uv": [0, 5], "uv_size": [1, 1]},
								"west": {"uv": [0, 5], "uv_size": [1, 1]},
								"up": {"uv": [1, 6], "uv_size": [-1, -1]},
								"down": {"uv": [1, 6], "uv_size": [-1, -1]}
							}
						}
					]
				},
				{
					"name": "armorLeftArmOut",
					"parent": "bone8",
					"pivot": [7.1, 24.1, 2],
					"cubes": [
						{
							"origin": [8.1, 19, -2.25],
							"size": [0.35, 4, 4.5],
							"uv": {
								"north": {"uv": [56, 53], "uv_size": [4, 4]},
								"east": {"uv": [60, 53], "uv_size": [-4, 5]},
								"south": {"uv": [56, 53], "uv_size": [4, 4]},
								"west": {"uv": [56, 53], "uv_size": [4, 4]},
								"up": {"uv": [57, 57], "uv_size": [-1, -4]},
								"down": {"uv": [60, 57], "uv_size": [-4, -1]}
							}
						},
						{
							"origin": [3.5, 21, -2.25],
							"size": [0.35, 3, 4.5],
							"uv": {
								"north": {"uv": [49, 52], "uv_size": [-1, 3]},
								"east": {"uv": [52, 52], "uv_size": [-4, 3]},
								"south": {"uv": [49, 52], "uv_size": [-1, 3]},
								"west": {"uv": [52, 52], "uv_size": [-4, 3]},
								"up": {"uv": [48, 53], "uv_size": [4, -1]},
								"down": {"uv": [48, 55], "uv_size": [4, -1]}
							}
						},
						{
							"origin": [8.1, 16, -2.25],
							"size": [0.35, 2, 4.5],
							"uv": {
								"north": {"uv": [58, 58], "uv_size": [1, 1]},
								"east": {"uv": [60, 58], "uv_size": [-3, 1]},
								"south": {"uv": [59, 58], "uv_size": [1, 1]},
								"west": {"uv": [56, 58], "uv_size": [4, 2]},
								"up": {"uv": [59, 59], "uv_size": [1, -1]},
								"down": {"uv": [59, 59], "uv_size": [1, -1]}
							}
						},
						{
							"origin": [3.6, 17, -2.25],
							"size": [0.35, 1, 4.5],
							"uv": {
								"north": {"uv": [60, 59], "uv_size": [1, 1]},
								"east": {"uv": [60, 59], "uv_size": [1, 1]},
								"south": {"uv": [60, 59], "uv_size": [1, 1]},
								"west": {"uv": [60, 59], "uv_size": [1, 1]},
								"up": {"uv": [61, 60], "uv_size": [-1, -1]},
								"down": {"uv": [61, 60], "uv_size": [-1, -1]}
							}
						},
						{
							"origin": [6.9, 23, 2.65],
							"size": [0.35, 1, 1.1],
							"pivot": [7.25, 23, 2.45],
							"rotation": [0, -90, 0],
							"uv": {
								"north": {"uv": [61, 52], "uv_size": [2, 1]},
								"east": {"uv": [61, 52], "uv_size": [2, 1]},
								"south": {"uv": [61, 52], "uv_size": [2, 1]},
								"west": {"uv": [61, 52], "uv_size": [2, 1]},
								"up": {"uv": [63, 53], "uv_size": [-2, -1]},
								"down": {"uv": [63, 53], "uv_size": [-2, -1]}
							}
						},
						{
							"origin": [8, 19, 2.55],
							"size": [0.35, 4, 2.4],
							"pivot": [8.35, 19, 2.45],
							"rotation": [0, -90, 0],
							"uv": {
								"north": {"uv": [60, 55], "uv_size": [1, 2]},
								"east": {"uv": [63, 55], "uv_size": [-3, 2]},
								"south": {"uv": [63, 59], "uv_size": [1, 1]},
								"west": {"uv": [60, 53], "uv_size": [2, 4]},
								"up": {"uv": [62, 57], "uv_size": [-2, -4]},
								"down": {"uv": [63, 56], "uv_size": [-2, -1]}
							}
						},
						{
							"origin": [8, 20, 4.85],
							"size": [0.35, 4, 2.1],
							"pivot": [8.35, 19, 2.45],
							"rotation": [0, -90, 0],
							"uv": {
								"north": {"uv": [60, 55], "uv_size": [1, 2]},
								"east": {"uv": [62, 52], "uv_size": [2, 4]},
								"south": {"uv": [63, 59], "uv_size": [1, 1]},
								"west": {"uv": [62, 52], "uv_size": [2, 4]},
								"up": {"uv": [64, 60], "uv_size": [-1, -1]},
								"down": {"uv": [63, 56], "uv_size": [-2, -1]}
							}
						},
						{
							"origin": [8, 17, 2.55],
							"size": [0.35, 1, 4.5],
							"pivot": [8.35, 17, 2.45],
							"rotation": [0, -90, 0],
							"uv": {
								"north": {"uv": [60, 59], "uv_size": [1, 1]},
								"east": {"uv": [60, 59], "uv_size": [1, 1]},
								"south": {"uv": [60, 59], "uv_size": [1, 1]},
								"west": {"uv": [60, 59], "uv_size": [1, 1]},
								"up": {"uv": [61, 60], "uv_size": [-1, -1]},
								"down": {"uv": [61, 60], "uv_size": [-1, -1]}
							}
						},
						{
							"origin": [7, 23, -2.05],
							"size": [0.35, 1, 3.4],
							"pivot": [7.25, 23, -2.15],
							"rotation": [0, -90, 0],
							"uv": {
								"north": {"uv": [54, 52], "uv_size": [1, 1]},
								"east": {"uv": [52, 52], "uv_size": [3, 1]},
								"south": {"uv": [53, 52], "uv_size": [1, 1]},
								"west": {"uv": [53, 52], "uv_size": [2, 1]},
								"up": {"uv": [54, 53], "uv_size": [-1, -1]},
								"down": {"uv": [54, 53], "uv_size": [-1, -1]}
							}
						},
						{
							"origin": [4.9, 17, -5.25],
							"size": [0.35, 1, 4.5],
							"pivot": [5.15, 16, -2.15],
							"rotation": [0, -90, 0],
							"uv": {
								"north": {"uv": [48, 58], "uv_size": [4, 1]},
								"east": {"uv": [60, 59], "uv_size": [1, 1]},
								"south": {"uv": [60, 59], "uv_size": [1, 1]},
								"west": {"uv": [60, 59], "uv_size": [1, 1]},
								"up": {"uv": [61, 60], "uv_size": [-1, -1]},
								"down": {"uv": [61, 60], "uv_size": [-1, -1]}
							}
						},
						{
							"origin": [8.1, 21, -2.05],
							"size": [0.35, 2, 4.5],
							"pivot": [8.35, 22, -2.15],
							"rotation": [0, -90, 0],
							"uv": {
								"north": {"uv": [54, 52], "uv_size": [1, 1]},
								"east": {"uv": [52, 53], "uv_size": [4, 2]},
								"south": {"uv": [53, 52], "uv_size": [1, 1]},
								"west": {"uv": [56, 53], "uv_size": [-4, 2]},
								"up": {"uv": [54, 53], "uv_size": [-1, -1]},
								"down": {"uv": [54, 53], "uv_size": [-1, -1]}
							}
						},
						{
							"origin": [8.1, 20, -2.05],
							"size": [0.35, 1, 3.4],
							"pivot": [8.35, 21, -2.15],
							"rotation": [0, -90, 0],
							"uv": {
								"north": {"uv": [54, 52], "uv_size": [1, 1]},
								"east": {"uv": [53, 55], "uv_size": [3, 1]},
								"south": {"uv": [53, 52], "uv_size": [1, 1]},
								"west": {"uv": [56, 53], "uv_size": [-4, 2]},
								"up": {"uv": [54, 53], "uv_size": [-1, -1]},
								"down": {"uv": [54, 53], "uv_size": [-1, -1]}
							}
						},
						{
							"origin": [8.1, 18.9, -2.05],
							"size": [0.35, 1.1, 2.5],
							"pivot": [8.35, 19, -2.15],
							"rotation": [0, -90, 0],
							"uv": {
								"north": {"uv": [54, 56], "uv_size": [2, 1]},
								"east": {"uv": [54, 56], "uv_size": [2, 1]},
								"south": {"uv": [54, 56], "uv_size": [2, 1]},
								"west": {"uv": [54, 56], "uv_size": [2, 1]},
								"up": {"uv": [56, 57], "uv_size": [-2, -1]},
								"down": {"uv": [56, 57], "uv_size": [-2, -1]}
							}
						},
						{
							"origin": [8.1, 13.9, -2.05],
							"size": [0.35, 1.1, 4.5],
							"pivot": [8.35, 15, -2.15],
							"rotation": [0, -90, 0],
							"uv": {
								"north": {"uv": [52, 61], "uv_size": [4, 1]},
								"east": {"uv": [52, 61], "uv_size": [4, 1]},
								"south": {"uv": [52, 61], "uv_size": [4, 1]},
								"west": {"uv": [56, 61], "uv_size": [-4, 1]},
								"up": {"uv": [54, 62], "uv_size": [-2, -1]},
								"down": {"uv": [54, 62], "uv_size": [-2, -1]}
							}
						},
						{
							"origin": [8.1, 13.9, 2.45],
							"size": [0.35, 1.1, 4.5],
							"pivot": [8.35, 15, 2.35],
							"rotation": [0, -90, 0],
							"uv": {
								"north": {"uv": [52, 61], "uv_size": [4, 1]},
								"east": {"uv": [52, 61], "uv_size": [4, 1]},
								"south": {"uv": [52, 61], "uv_size": [4, 1]},
								"west": {"uv": [56, 61], "uv_size": [-4, 1]},
								"up": {"uv": [54, 62], "uv_size": [-2, -1]},
								"down": {"uv": [54, 62], "uv_size": [-2, -1]}
							}
						},
						{
							"origin": [8.1, 13.9, -2.25],
							"size": [0.35, 1.1, 4.5],
							"uv": {
								"north": {"uv": [56, 61], "uv_size": [4, 1]},
								"east": {"uv": [56, 61], "uv_size": [4, 1]},
								"south": {"uv": [56, 61], "uv_size": [4, 1]},
								"west": {"uv": [54, 61], "uv_size": [4, 1]},
								"up": {"uv": [60, 62], "uv_size": [-4, -1]},
								"down": {"uv": [60, 62], "uv_size": [-4, -1]}
							}
						},
						{
							"origin": [3.6, 13.9, -2.25],
							"size": [0.35, 1.1, 4.5],
							"uv": {
								"north": {"uv": [53, 61], "uv_size": [-4, 1]},
								"east": {"uv": [53, 61], "uv_size": [-4, 1]},
								"south": {"uv": [53, 61], "uv_size": [-4, 1]},
								"west": {"uv": [53, 61], "uv_size": [-4, 1]},
								"up": {"uv": [49, 62], "uv_size": [4, -1]},
								"down": {"uv": [49, 62], "uv_size": [4, -1]}
							}
						},
						{
							"origin": [3.8, 24, -2.3],
							"size": [3.3, 0.2, 4.5],
							"uv": {
								"north": {"uv": [53, 48], "uv_size": [2, 1]},
								"east": {"uv": [55, 49], "uv_size": [-1, 2]},
								"south": {"uv": [55, 48], "uv_size": [-2, 1]},
								"west": {"uv": [55, 49], "uv_size": [-1, 2]},
								"up": {"uv": [52, 52], "uv_size": [3, -4]},
								"down": {"uv": [53, 52], "uv_size": [2, -4]}
							}
						},
						{
							"origin": [7.1, 24, -1.3],
							"size": [1.1, 0.2, 2.5],
							"uv": {
								"north": {"uv": [56, 49], "uv_size": [-1, 2]},
								"east": {"uv": [56, 49], "uv_size": [-1, 2]},
								"south": {"uv": [56, 49], "uv_size": [-1, 2]},
								"west": {"uv": [56, 49], "uv_size": [-1, 2]},
								"up": {"uv": [55, 51], "uv_size": [1, -2]},
								"down": {"uv": [55, 51], "uv_size": [1, -2]}
							}
						}
					]
				},
				{
					"name": "bipedRightLeg",
					"pivot": [-2, 12, 0]
				},
				{
					"name": "armorRightLeg",
					"parent": "bipedRightLeg",
					"pivot": [-2, 12, 0]
				},
				{
					"name": "bone6",
					"parent": "armorRightLeg",
					"pivot": [-4, 22, 0],
					"cubes": [
						{
							"origin": [-0.1, 0.2, -2.2],
							"size": [4.4, 11.8, 4.4],
							"uv": {
								"north": {"uv": [8, 20], "uv_size": [-4, 12]},
								"east": {"uv": [12, 20], "uv_size": [-4, 12]},
								"south": {"uv": [16, 20], "uv_size": [-4, 12]},
								"west": {"uv": [4, 20], "uv_size": [-4, 12]},
								"up": {"uv": [8, 20], "uv_size": [-4, -4]},
								"down": {"uv": [12, 20], "uv_size": [-4, -4]}
							}
						}
					]
				},
				{
					"name": "armorRightBoot",
					"parent": "bipedRightLeg",
					"pivot": [-2, 12, 0]
				},
				{
					"name": "bone9",
					"parent": "armorRightBoot",
					"pivot": [-4, 22, 0]
				},
				{
					"name": "bone11",
					"parent": "bone9",
					"pivot": [-4, 22, 0],
					"cubes": [
						{
							"origin": [0, -0.3, -2.3],
							"size": [4.6, 1.2, 4.6],
							"uv": {
								"north": {"uv": [4, 52], "uv_size": [4, 12]},
								"east": {"uv": [0, 52], "uv_size": [4, 12]},
								"south": {"uv": [12, 52], "uv_size": [4, 12]},
								"west": {"uv": [8, 52], "uv_size": [4, 12]},
								"up": {"uv": [12, 20], "uv_size": [-4, -4]},
								"down": {"uv": [12, 20], "uv_size": [-4, -4]}
							}
						},
						{
							"origin": [0, 3.8, -2.5],
							"size": [4.6, 1.1, 0.3],
							"uv": {
								"north": {"uv": [4, 59], "uv_size": [4, 1]},
								"east": {"uv": [4, 59], "uv_size": [4, 1]},
								"south": {"uv": [4, 59], "uv_size": [4, 1]},
								"west": {"uv": [4, 59], "uv_size": [4, 1]},
								"up": {"uv": [8, 60], "uv_size": [-4, -1]},
								"down": {"uv": [8, 60], "uv_size": [-4, -1]}
							}
						},
						{
							"origin": [1, 4.9, -2.5],
							"size": [2.6, 1, 0.3],
							"uv": {
								"north": {"uv": [4, 59], "uv_size": [4, 1]},
								"east": {"uv": [4, 59], "uv_size": [4, 1]},
								"south": {"uv": [4, 59], "uv_size": [4, 1]},
								"west": {"uv": [4, 59], "uv_size": [4, 1]},
								"up": {"uv": [8, 60], "uv_size": [-4, -1]},
								"down": {"uv": [8, 60], "uv_size": [-4, -1]}
							}
						},
						{
							"origin": [1, 2.8, -2.5],
							"size": [2.6, 1, 0.3],
							"uv": {
								"north": {"uv": [4, 59], "uv_size": [4, 1]},
								"east": {"uv": [4, 59], "uv_size": [4, 1]},
								"south": {"uv": [4, 59], "uv_size": [4, 1]},
								"west": {"uv": [4, 59], "uv_size": [4, 1]},
								"up": {"uv": [8, 60], "uv_size": [-4, -1]},
								"down": {"uv": [8, 60], "uv_size": [-4, -1]}
							}
						},
						{
							"origin": [0, -0.2, -2.5],
							"size": [4.6, 1.1, 0.7],
							"uv": {
								"north": {"uv": [4, 63], "uv_size": [4, 1]},
								"east": {"uv": [4, 63], "uv_size": [4, 1]},
								"south": {"uv": [4, 63], "uv_size": [4, 1]},
								"west": {"uv": [4, 63], "uv_size": [4, 1]},
								"up": {"uv": [8, 64], "uv_size": [-4, -1]},
								"down": {"uv": [8, 64], "uv_size": [-4, -1]}
							}
						},
						{
							"origin": [3.3, 7.7, -2.5],
							"size": [1.3, 3.2, 0.3],
							"uv": {
								"north": {"uv": [7, 53], "uv_size": [1, 3]},
								"east": {"uv": [7, 53], "uv_size": [1, 3]},
								"south": {"uv": [7, 53], "uv_size": [1, 3]},
								"west": {"uv": [7, 53], "uv_size": [1, 3]},
								"up": {"uv": [8, 56], "uv_size": [-1, -3]},
								"down": {"uv": [8, 56], "uv_size": [-1, -1]}
							}
						},
						{
							"origin": [3.3, 7.7, -2.5],
							"size": [1.3, 3.2, 0.3],
							"uv": {
								"north": {"uv": [7, 53], "uv_size": [1, 3]},
								"east": {"uv": [7, 53], "uv_size": [1, 3]},
								"south": {"uv": [7, 53], "uv_size": [1, 3]},
								"west": {"uv": [7, 53], "uv_size": [1, 3]},
								"up": {"uv": [8, 56], "uv_size": [-1, -3]},
								"down": {"uv": [8, 56], "uv_size": [-1, -3]}
							}
						},
						{
							"origin": [3.3, 7.7, -2.5],
							"size": [1.3, 3.2, 0.3],
							"uv": {
								"north": {"uv": [7, 53], "uv_size": [1, 3]},
								"east": {"uv": [7, 53], "uv_size": [1, 3]},
								"south": {"uv": [7, 53], "uv_size": [1, 3]},
								"west": {"uv": [7, 53], "uv_size": [1, 3]},
								"up": {"uv": [8, 56], "uv_size": [-1, -3]},
								"down": {"uv": [8, 56], "uv_size": [-1, -3]}
							}
						},
						{
							"origin": [2.3, 7.7, 2.2],
							"size": [2.3, 3.2, 0.3],
							"uv": {
								"north": {"uv": [14, 53], "uv_size": [-2, 3]},
								"east": {"uv": [13, 53], "uv_size": [1, 3]},
								"south": {"uv": [12, 53], "uv_size": [2, 3]},
								"west": {"uv": [12, 53], "uv_size": [1, 3]},
								"up": {"uv": [8, 56], "uv_size": [-1, -3]},
								"down": {"uv": [8, 56], "uv_size": [-1, -3]}
							}
						},
						{
							"origin": [4.6, -0.2, 2],
							"size": [4.6, 1.1, 0.5],
							"pivot": [4.6, -0.2, 2.3],
							"rotation": [0, 90, 0],
							"uv": {
								"north": {"uv": [8, 63], "uv_size": [4, 1]},
								"east": {"uv": [8, 63], "uv_size": [4, 1]},
								"south": {"uv": [8, 63], "uv_size": [4, 1]},
								"west": {"uv": [8, 63], "uv_size": [4, 1]},
								"up": {"uv": [12, 64], "uv_size": [-4, -1]},
								"down": {"uv": [12, 64], "uv_size": [-4, -1]}
							}
						},
						{
							"origin": [6.9, 10.9, 2.2],
							"size": [2.3, 1, 0.3],
							"pivot": [4.6, 3.7, 2.3],
							"rotation": [0, 90, 0],
							"uv": {
								"north": {"uv": [8, 52], "uv_size": [2, 1]},
								"east": {"uv": [8, 52], "uv_size": [2, 1]},
								"south": {"uv": [8, 52], "uv_size": [2, 1]},
								"west": {"uv": [8, 52], "uv_size": [2, 1]},
								"up": {"uv": [10, 53], "uv_size": [-2, -1]},
								"down": {"uv": [10, 53], "uv_size": [-2, -1]}
							}
						},
						{
							"origin": [4.6, 7.7, 2.2],
							"size": [4.6, 3.2, 0.3],
							"pivot": [4.6, 3.7, 2.3],
							"rotation": [0, 90, 0],
							"uv": {
								"north": {"uv": [12, 53], "uv_size": [-4, 3]},
								"east": {"uv": [11, 53], "uv_size": [1, 3]},
								"south": {"uv": [8, 53], "uv_size": [4, 3]},
								"west": {"uv": [8, 53], "uv_size": [1, 3]},
								"up": {"uv": [12, 54], "uv_size": [-4, -1]},
								"down": {"uv": [12, 56], "uv_size": [-4, -1]}
							}
						},
						{
							"origin": [-0.2, 3.8, 2.3],
							"size": [4.6, 1.1, 0.3],
							"pivot": [-0.2, 3.8, 2.3],
							"rotation": [0, 90, 0],
							"uv": {
								"north": {"uv": [0, 59], "uv_size": [4, 1]},
								"east": {"uv": [0, 59], "uv_size": [3, 1]},
								"south": {"uv": [4, 59], "uv_size": [-4, 1]},
								"west": {"uv": [3, 59], "uv_size": [1, 1]},
								"up": {"uv": [0, 60], "uv_size": [4, -1]},
								"down": {"uv": [0, 60], "uv_size": [4, -1]}
							}
						},
						{
							"origin": [4.5, 3.8, 2.3],
							"size": [4.6, 1.1, 0.3],
							"pivot": [4.5, 3.8, 2.3],
							"rotation": [0, 90, 0],
							"uv": {
								"north": {"uv": [0, 59], "uv_size": [4, 1]},
								"east": {"uv": [0, 59], "uv_size": [3, 1]},
								"south": {"uv": [4, 59], "uv_size": [-4, 1]},
								"west": {"uv": [3, 59], "uv_size": [1, 1]},
								"up": {"uv": [0, 60], "uv_size": [4, -1]},
								"down": {"uv": [0, 60], "uv_size": [4, -1]}
							}
						},
						{
							"origin": [-0.2, -0.2, 2.3],
							"size": [4.6, 1.1, 0.4],
							"pivot": [-0.2, -0.2, 2.3],
							"rotation": [0, 90, 0],
							"uv": {
								"north": {"uv": [12, 63], "uv_size": [-4, 1]},
								"east": {"uv": [12, 63], "uv_size": [-4, 1]},
								"south": {"uv": [12, 63], "uv_size": [-4, 1]},
								"west": {"uv": [12, 63], "uv_size": [-4, 1]},
								"up": {"uv": [8, 64], "uv_size": [4, -1]},
								"down": {"uv": [8, 64], "uv_size": [4, -1]}
							}
						},
						{
							"origin": [0, -0.2, 2.1],
							"size": [4.6, 2.1, 0.4],
							"uv": {
								"north": {"uv": [12, 62], "uv_size": [4, 2]},
								"east": {"uv": [12, 62], "uv_size": [4, 2]},
								"south": {"uv": [12, 62], "uv_size": [4, 2]},
								"west": {"uv": [12, 62], "uv_size": [4, 2]},
								"up": {"uv": [16, 64], "uv_size": [-4, -2]},
								"down": {"uv": [16, 64], "uv_size": [-4, -2]}
							}
						},
						{
							"origin": [0.1, 3.9, 2.1],
							"size": [4.5, 1, 0.4],
							"uv": {
								"north": {"uv": [12, 59], "uv_size": [4, 1]},
								"east": {"uv": [12, 59], "uv_size": [4, 1]},
								"south": {"uv": [12, 59], "uv_size": [4, 1]},
								"west": {"uv": [12, 59], "uv_size": [4, 1]},
								"up": {"uv": [16, 60], "uv_size": [-4, -1]},
								"down": {"uv": [16, 60], "uv_size": [-4, -1]}
							}
						},
						{
							"origin": [3.4, 3.9, 1.9],
							"size": [1.2, 1, 0.6],
							"uv": {
								"north": {"uv": [13, 61], "uv_size": [2, 1]},
								"east": {"uv": [13, 61], "uv_size": [2, 1]},
								"south": {"uv": [13, 61], "uv_size": [2, 1]},
								"west": {"uv": [13, 61], "uv_size": [2, 1]},
								"up": {"uv": [15, 62], "uv_size": [-2, -1]},
								"down": {"uv": [15, 62], "uv_size": [-2, -1]}
							}
						},
						{
							"origin": [1.1, 0.9, -2.5],
							"size": [2.4, 1, 0.3],
							"uv": {
								"north": {"uv": [5, 60], "uv_size": [2, 1]},
								"east": {"uv": [5, 60], "uv_size": [2, 1]},
								"south": {"uv": [5, 60], "uv_size": [2, 1]},
								"west": {"uv": [5, 60], "uv_size": [2, 1]},
								"up": {"uv": [7, 61], "uv_size": [-2, -1]},
								"down": {"uv": [7, 61], "uv_size": [-2, -1]}
							}
						},
						{
							"origin": [0.1, 0.9, -0.1],
							"size": [2.4, 1, 0.3],
							"pivot": [0.1, 0.8, -0.1],
							"rotation": [0, -90, 0],
							"uv": {
								"north": {"uv": [10, 62], "uv_size": [2, 1]},
								"east": {"uv": [10, 62], "uv_size": [2, 1]},
								"south": {"uv": [10, 62], "uv_size": [2, 1]},
								"west": {"uv": [10, 62], "uv_size": [2, 1]},
								"up": {"uv": [12, 63], "uv_size": [-2, -1]},
								"down": {"uv": [12, 63], "uv_size": [-2, -1]}
							}
						},
						{
							"origin": [4.8, 0.9, -0.1],
							"size": [2.4, 1, 0.3],
							"pivot": [4.8, 0.8, -0.1],
							"rotation": [0, -90, 0],
							"uv": {
								"north": {"uv": [10, 62], "uv_size": [2, 1]},
								"east": {"uv": [10, 62], "uv_size": [2, 1]},
								"south": {"uv": [10, 62], "uv_size": [2, 1]},
								"west": {"uv": [10, 62], "uv_size": [2, 1]},
								"up": {"uv": [12, 63], "uv_size": [-2, -1]},
								"down": {"uv": [12, 63], "uv_size": [-2, -1]}
							}
						}
					]
				},
				{
					"name": "bipedLeftLeg",
					"pivot": [2, 12, 0]
				},
				{
					"name": "armorLeftLeg",
					"parent": "bipedLeftLeg",
					"pivot": [2, 12, 0]
				},
				{
					"name": "bone7",
					"parent": "armorLeftLeg",
					"pivot": [-4, 22, 0],
					"cubes": [
						{
							"origin": [-4.1, 0.2, -2.2],
							"size": [4.4, 11.8, 4.4],
							"uv": {
								"north": {"uv": [24, 52], "uv_size": [-4, 12]},
								"east": {"uv": [28, 52], "uv_size": [-4, 12]},
								"south": {"uv": [32, 52], "uv_size": [-4, 12]},
								"west": {"uv": [20, 52], "uv_size": [-4, 12]},
								"up": {"uv": [4, 20], "uv_size": [4, -4]},
								"down": {"uv": [8, 4], "uv_size": [4, -4]}
							}
						}
					]
				},
				{
					"name": "armorLeftBoot",
					"parent": "bipedLeftLeg",
					"pivot": [2, 12, 0]
				},
				{
					"name": "bone10",
					"parent": "armorLeftBoot",
					"pivot": [-4, 22, 0],
					"cubes": [
						{
							"origin": [-4.2, -0.3, -2.3],
							"size": [4.6, 1.2, 4.6],
							"uv": {
								"north": {"uv": [8, 52], "uv_size": [-4, 12]},
								"east": {"uv": [12, 52], "uv_size": [-4, 12]},
								"south": {"uv": [16, 52], "uv_size": [-4, 12]},
								"west": {"uv": [4, 52], "uv_size": [-4, 12]},
								"up": {"uv": [8, 20], "uv_size": [4, -4]},
								"down": {"uv": [8, 20], "uv_size": [4, -4]}
							}
						},
						{
							"origin": [-4.6, 3.8, -2.5],
							"size": [4.6, 1.1, 0.3],
							"uv": {
								"north": {"uv": [8, 59], "uv_size": [-4, 1]},
								"east": {"uv": [8, 59], "uv_size": [-4, 1]},
								"south": {"uv": [8, 59], "uv_size": [-4, 1]},
								"west": {"uv": [8, 59], "uv_size": [-4, 1]},
								"up": {"uv": [4, 60], "uv_size": [4, -1]},
								"down": {"uv": [4, 60], "uv_size": [4, -1]}
							}
						},
						{
							"origin": [-3.6, 4.9, -2.5],
							"size": [2.6, 1, 0.3],
							"uv": {
								"north": {"uv": [8, 59], "uv_size": [-4, 1]},
								"east": {"uv": [8, 59], "uv_size": [-4, 1]},
								"south": {"uv": [8, 59], "uv_size": [-4, 1]},
								"west": {"uv": [8, 59], "uv_size": [-4, 1]},
								"up": {"uv": [4, 60], "uv_size": [4, -1]},
								"down": {"uv": [4, 60], "uv_size": [4, -1]}
							}
						},
						{
							"origin": [-3.6, 2.8, -2.5],
							"size": [2.6, 1, 0.3],
							"uv": {
								"north": {"uv": [8, 59], "uv_size": [-4, 1]},
								"east": {"uv": [8, 59], "uv_size": [-4, 1]},
								"south": {"uv": [8, 59], "uv_size": [-4, 1]},
								"west": {"uv": [8, 59], "uv_size": [-4, 1]},
								"up": {"uv": [4, 60], "uv_size": [4, -1]},
								"down": {"uv": [4, 60], "uv_size": [4, -1]}
							}
						},
						{
							"origin": [-4.6, -0.2, -2.5],
							"size": [4.6, 1.1, 0.7],
							"uv": {
								"north": {"uv": [8, 63], "uv_size": [-4, 1]},
								"east": {"uv": [8, 63], "uv_size": [-4, 1]},
								"south": {"uv": [8, 63], "uv_size": [-4, 1]},
								"west": {"uv": [8, 63], "uv_size": [-4, 1]},
								"up": {"uv": [4, 64], "uv_size": [4, -1]},
								"down": {"uv": [4, 64], "uv_size": [4, -1]}
							}
						},
						{
							"origin": [-4.6, 7.7, -2.5],
							"size": [1.3, 3.2, 0.3],
							"uv": {
								"north": {"uv": [8, 53], "uv_size": [-1, 3]},
								"east": {"uv": [8, 53], "uv_size": [-1, 3]},
								"south": {"uv": [8, 53], "uv_size": [-1, 3]},
								"west": {"uv": [8, 53], "uv_size": [-1, 3]},
								"up": {"uv": [7, 56], "uv_size": [1, -3]},
								"down": {"uv": [7, 56], "uv_size": [1, -1]}
							}
						},
						{
							"origin": [-4.6, 7.7, -2.5],
							"size": [1.3, 3.2, 0.3],
							"uv": {
								"north": {"uv": [8, 53], "uv_size": [-1, 3]},
								"east": {"uv": [8, 53], "uv_size": [-1, 3]},
								"south": {"uv": [8, 53], "uv_size": [-1, 3]},
								"west": {"uv": [8, 53], "uv_size": [-1, 3]},
								"up": {"uv": [7, 56], "uv_size": [1, -3]},
								"down": {"uv": [7, 56], "uv_size": [1, -3]}
							}
						},
						{
							"origin": [-4.6, 7.7, -2.5],
							"size": [1.3, 3.2, 0.3],
							"uv": {
								"north": {"uv": [8, 53], "uv_size": [-1, 3]},
								"east": {"uv": [8, 53], "uv_size": [-1, 3]},
								"south": {"uv": [8, 53], "uv_size": [-1, 3]},
								"west": {"uv": [8, 53], "uv_size": [-1, 3]},
								"up": {"uv": [7, 56], "uv_size": [1, -3]},
								"down": {"uv": [7, 56], "uv_size": [1, -3]}
							}
						},
						{
							"origin": [-4.6, 7.7, 2.2],
							"size": [2.3, 3.2, 0.3],
							"uv": {
								"north": {"uv": [12, 53], "uv_size": [2, 3]},
								"east": {"uv": [13, 53], "uv_size": [-1, 3]},
								"south": {"uv": [14, 53], "uv_size": [-2, 3]},
								"west": {"uv": [14, 53], "uv_size": [-1, 3]},
								"up": {"uv": [7, 56], "uv_size": [1, -3]},
								"down": {"uv": [7, 56], "uv_size": [1, -3]}
							}
						},
						{
							"origin": [-9.2, -0.2, 2],
							"size": [4.6, 1.1, 0.5],
							"pivot": [-4.6, -0.2, 2.3],
							"rotation": [0, -90, 0],
							"uv": {
								"north": {"uv": [12, 63], "uv_size": [-4, 1]},
								"east": {"uv": [12, 63], "uv_size": [-4, 1]},
								"south": {"uv": [12, 63], "uv_size": [-4, 1]},
								"west": {"uv": [12, 63], "uv_size": [-4, 1]},
								"up": {"uv": [8, 64], "uv_size": [4, -1]},
								"down": {"uv": [8, 64], "uv_size": [4, -1]}
							}
						},
						{
							"origin": [-9.2, 10.9, 2.2],
							"size": [2.3, 1, 0.3],
							"pivot": [-4.6, 3.7, 2.3],
							"rotation": [0, -90, 0],
							"uv": {
								"north": {"uv": [10, 52], "uv_size": [-2, 1]},
								"east": {"uv": [10, 52], "uv_size": [-2, 1]},
								"south": {"uv": [10, 52], "uv_size": [-2, 1]},
								"west": {"uv": [10, 52], "uv_size": [-2, 1]},
								"up": {"uv": [8, 53], "uv_size": [2, -1]},
								"down": {"uv": [8, 53], "uv_size": [2, -1]}
							}
						},
						{
							"origin": [-9.2, 7.7, 2.2],
							"size": [4.6, 3.2, 0.3],
							"pivot": [-4.6, 3.7, 2.3],
							"rotation": [0, -90, 0],
							"uv": {
								"north": {"uv": [8, 53], "uv_size": [4, 3]},
								"east": {"uv": [9, 53], "uv_size": [-1, 3]},
								"south": {"uv": [12, 53], "uv_size": [-4, 3]},
								"west": {"uv": [12, 53], "uv_size": [-1, 3]},
								"up": {"uv": [8, 54], "uv_size": [4, -1]},
								"down": {"uv": [8, 56], "uv_size": [4, -1]}
							}
						},
						{
							"origin": [-4.4, 3.8, 2.3],
							"size": [4.6, 1.1, 0.3],
							"pivot": [0.2, 3.8, 2.3],
							"rotation": [0, -90, 0],
							"uv": {
								"north": {"uv": [4, 59], "uv_size": [-4, 1]},
								"east": {"uv": [4, 59], "uv_size": [-1, 1]},
								"south": {"uv": [0, 59], "uv_size": [4, 1]},
								"west": {"uv": [3, 59], "uv_size": [-3, 1]},
								"up": {"uv": [4, 60], "uv_size": [-4, -1]},
								"down": {"uv": [4, 60], "uv_size": [-4, -1]}
							}
						},
						{
							"origin": [-9.1, 3.8, 2.3],
							"size": [4.6, 1.1, 0.3],
							"pivot": [-4.5, 3.8, 2.3],
							"rotation": [0, -90, 0],
							"uv": {
								"north": {"uv": [4, 59], "uv_size": [-4, 1]},
								"east": {"uv": [4, 59], "uv_size": [-1, 1]},
								"south": {"uv": [0, 59], "uv_size": [4, 1]},
								"west": {"uv": [3, 59], "uv_size": [-3, 1]},
								"up": {"uv": [4, 60], "uv_size": [-4, -1]},
								"down": {"uv": [4, 60], "uv_size": [-4, -1]}
							}
						},
						{
							"origin": [-4.4, -0.2, 2.3],
							"size": [4.6, 1.1, 0.4],
							"pivot": [0.2, -0.2, 2.3],
							"rotation": [0, -90, 0],
							"uv": {
								"north": {"uv": [8, 63], "uv_size": [4, 1]},
								"east": {"uv": [8, 63], "uv_size": [4, 1]},
								"south": {"uv": [8, 63], "uv_size": [4, 1]},
								"west": {"uv": [8, 63], "uv_size": [4, 1]},
								"up": {"uv": [12, 64], "uv_size": [-4, -1]},
								"down": {"uv": [12, 64], "uv_size": [-4, -1]}
							}
						},
						{
							"origin": [-4.6, -0.2, 2.1],
							"size": [4.6, 2.1, 0.4],
							"uv": {
								"north": {"uv": [16, 62], "uv_size": [-4, 2]},
								"east": {"uv": [16, 62], "uv_size": [-4, 2]},
								"south": {"uv": [16, 62], "uv_size": [-4, 2]},
								"west": {"uv": [16, 62], "uv_size": [-4, 2]},
								"up": {"uv": [12, 64], "uv_size": [4, -2]},
								"down": {"uv": [12, 64], "uv_size": [4, -2]}
							}
						},
						{
							"origin": [-4.6, 3.9, 2.1],
							"size": [4.5, 1, 0.4],
							"uv": {
								"north": {"uv": [16, 59], "uv_size": [-4, 1]},
								"east": {"uv": [16, 59], "uv_size": [-4, 1]},
								"south": {"uv": [16, 59], "uv_size": [-4, 1]},
								"west": {"uv": [16, 59], "uv_size": [-4, 1]},
								"up": {"uv": [12, 60], "uv_size": [4, -1]},
								"down": {"uv": [12, 60], "uv_size": [4, -1]}
							}
						},
						{
							"origin": [-4.6, 3.9, 1.9],
							"size": [1.2, 1, 0.6],
							"uv": {
								"north": {"uv": [15, 61], "uv_size": [-2, 1]},
								"east": {"uv": [15, 61], "uv_size": [-2, 1]},
								"south": {"uv": [15, 61], "uv_size": [-2, 1]},
								"west": {"uv": [15, 61], "uv_size": [-2, 1]},
								"up": {"uv": [13, 62], "uv_size": [2, -1]},
								"down": {"uv": [13, 62], "uv_size": [2, -1]}
							}
						},
						{
							"origin": [-3.5, 0.9, -2.5],
							"size": [2.4, 1, 0.3],
							"uv": {
								"north": {"uv": [7, 60], "uv_size": [-2, 1]},
								"east": {"uv": [7, 60], "uv_size": [-2, 1]},
								"south": {"uv": [7, 60], "uv_size": [-2, 1]},
								"west": {"uv": [7, 60], "uv_size": [-2, 1]},
								"up": {"uv": [5, 61], "uv_size": [2, -1]},
								"down": {"uv": [5, 61], "uv_size": [2, -1]}
							}
						},
						{
							"origin": [-2.5, 0.9, -0.1],
							"size": [2.4, 1, 0.3],
							"pivot": [-0.1, 0.8, -0.1],
							"rotation": [0, 90, 0],
							"uv": {
								"north": {"uv": [12, 62], "uv_size": [-2, 1]},
								"east": {"uv": [12, 62], "uv_size": [-2, 1]},
								"south": {"uv": [12, 62], "uv_size": [-2, 1]},
								"west": {"uv": [12, 62], "uv_size": [-2, 1]},
								"up": {"uv": [10, 63], "uv_size": [2, -1]},
								"down": {"uv": [10, 63], "uv_size": [2, -1]}
							}
						},
						{
							"origin": [-7.2, 0.9, -0.1],
							"size": [2.4, 1, 0.3],
							"pivot": [-4.8, 0.8, -0.1],
							"rotation": [0, 90, 0],
							"uv": {
								"north": {"uv": [12, 62], "uv_size": [-2, 1]},
								"east": {"uv": [12, 62], "uv_size": [-2, 1]},
								"south": {"uv": [12, 62], "uv_size": [-2, 1]},
								"west": {"uv": [12, 62], "uv_size": [-2, 1]},
								"up": {"uv": [10, 63], "uv_size": [2, -1]},
								"down": {"uv": [10, 63], "uv_size": [2, -1]}
							}
						}
					]
				}
			]
		}
	]
}